rtl/core/preprocessing/intersection.sv
module intersection #(
    parameter WIDTH = 20  // 1 sign + 11 int + 8 frac = 20 bits, "12.8" format
)(
    input  logic                    clk_i,
    input  logic                    start_i,
    
    // Line segment endpoints (v1 to v2), each in 12.8 fixed point
    input  logic signed [WIDTH-1:0] v1_x,
    input  logic signed [WIDTH-1:0] v1_y,
    input  logic signed [WIDTH-1:0] v1_z,
    input  logic signed [WIDTH-1:0] v1_w,
    input  logic signed [WIDTH-1:0] v2_x,
    input  logic signed [WIDTH-1:0] v2_y,
    input  logic signed [WIDTH-1:0] v2_z,
    input  logic signed [WIDTH-1:0] v2_w,
    
    // Plane coefficients (a,b,c,d), each in 12.8 fixed point
    input  logic signed [WIDTH-1:0] plane_a,
    input  logic signed [WIDTH-1:0] plane_b,
    input  logic signed [WIDTH-1:0] plane_c,
    input  logic signed [WIDTH-1:0] plane_d,
    
    // Intersection point output in 12.8 fixed point (on segment)
    output logic signed [WIDTH-1:0] intersect_x,
    output logic signed [WIDTH-1:0] intersect_y,
    output logic signed [WIDTH-1:0] intersect_z,
    output logic signed [WIDTH-1:0] intersect_w,
    
    output logic                    done_o
);

always_ff @(posedge clk_i) begin
    if (start_i) begin
        // 64-bit accumulators to avoid overflow
        logic signed [63:0] sum_v1, sum_diff;
        logic signed [63:0] num, den;
        logic signed [63:0] t_raw;      // t in Q16, before clamping
        logic signed [63:0] t_clamped;  // t in Q16, clamped to [0,1]

        // For reference: 1.0 in Q16 is 65536
        localparam logic signed [63:0] Q16_ZERO = 64'd0;
        localparam logic signed [63:0] Q16_ONE  = 64'd65536;

        //====================
        //   plane . v1  (Q16)
        //====================
        sum_v1 = (plane_a * v1_x)
               + (plane_b * v1_y)
               + (plane_c * v1_z)
               + (plane_d * v1_w);

        // num = -(plane . v1)
        num = -sum_v1;  // Q16

        //==============================
        //   plane . (v2 - v1)  (Q16)
        //==============================
        sum_diff = (plane_a * (v2_x - v1_x))
                 + (plane_b * (v2_y - v1_y))
                 + (plane_c * (v2_z - v1_z))
                 + (plane_d * (v2_w - v1_w));
        den = sum_diff; // Q16

        //====================
        // Compute t = num / den in Q16
        // => t = (num << 16) / den
        //====================
        if (den == 0) begin
            // Degenerate: line parallel to plane => no intersection or infinite
            t_raw = 0;
        end
        else begin
            t_raw = (num <<< 16) / den;  
        end

        //====================
        // Clamp t to [0, 1] in Q16
        //====================
        if (t_raw < Q16_ZERO) begin
            t_clamped = Q16_ZERO;  // means intersection is effectively at v1
        end
        else if (t_raw > Q16_ONE) begin
            t_clamped = Q16_ONE;   // means intersection is effectively at v2
        end
        else begin
            t_clamped = t_raw;
        end

        //=========================================
        // Intersection in Q8 (clamped to segment):
        //   intersect = v1 + [t_clamped * (v2 - v1) >> 16]
        //=========================================
        intersect_x <= v1_x + ((t_clamped * (v2_x - v1_x)) >>> 16);
        intersect_y <= v1_y + ((t_clamped * (v2_y - v1_y)) >>> 16);
        intersect_z <= v1_z + ((t_clamped * (v2_z - v1_z)) >>> 16);
        intersect_w <= v1_w + ((t_clamped * (v2_w - v1_w)) >>> 16);

        done_o <= 1'b1;
    end
    else begin
        done_o <= 1'b0;
    end
end

endmodule

tb/test/core/preprocessing/dump.vcd
$version Generated by VerilatedVcd $end
$timescale 1ps $end
 $var wire 1 # clk_i $end
 $var wire 1 $ start_i $end
 $var wire 20 % v1_x [19:0] $end
 $var wire 20 & v1_y [19:0] $end
 $var wire 20 ' v1_z [19:0] $end
 $var wire 20 ( v1_w [19:0] $end
 $var wire 20 ) v2_x [19:0] $end
 $var wire 20 * v2_y [19:0] $end
 $var wire 20 + v2_z [19:0] $end
 $var wire 20 , v2_w [19:0] $end
 $var wire 20 - plane_a [19:0] $end
 $var wire 20 . plane_b [19:0] $end
 $var wire 20 / plane_c [19:0] $end
 $var wire 20 0 plane_d [19:0] $end
 $var wire 20 1 intersect_x [19:0] $end
 $var wire 20 2 intersect_y [19:0] $end
 $var wire 20 3 intersect_z [19:0] $end
 $var wire 20 4 intersect_w [19:0] $end
 $var wire 1 5 done_o $end
 $scope module intersection $end
  $var wire 32 U WIDTH [31:0] $end
  $var wire 1 6 clk_i $end
  $var wire 1 7 start_i $end
  $var wire 20 8 v1_x [19:0] $end
  $var wire 20 9 v1_y [19:0] $end
  $var wire 20 : v1_z [19:0] $end
  $var wire 20 ; v1_w [19:0] $end
  $var wire 20 < v2_x [19:0] $end
  $var wire 20 = v2_y [19:0] $end
  $var wire 20 > v2_z [19:0] $end
  $var wire 20 ? v2_w [19:0] $end
  $var wire 20 @ plane_a [19:0] $end
  $var wire 20 A plane_b [19:0] $end
  $var wire 20 B plane_c [19:0] $end
  $var wire 20 C plane_d [19:0] $end
  $var wire 20 D intersect_x [19:0] $end
  $var wire 20 E intersect_y [19:0] $end
  $var wire 20 F intersect_z [19:0] $end
  $var wire 20 G intersect_w [19:0] $end
  $var wire 1 H done_o $end
  $scope module unnamedblk1 $end
   $var wire 64 I sum_v1 [63:0] $end
   $var wire 64 K sum_diff [63:0] $end
   $var wire 64 M num [63:0] $end
   $var wire 64 O den [63:0] $end
   $var wire 64 Q t_raw [63:0] $end
   $var wire 64 S t_clamped [63:0] $end
   $var wire 64 V Q16_ZERO [63:0] $end
   $var wire 64 X Q16_ONE [63:0] $end
  $upscope $end
 $upscope $end
$enddefinitions $end


#0
1#
0$
b00000000000000000000 %
b00000000000000000000 &
b00000000000000000000 '
b00000000000000000000 (
b00000000000000000000 )
b00000000000000000000 *
b00000000000000000000 +
b00000000000000000000 ,
b00000000000000000000 -
b00000000000000000000 .
b00000000000000000000 /
b00000000000000000000 0
b00000000000000000000 1
b00000000000000000000 2
b00000000000000000000 3
b00000000000000000000 4
05
16
07
b00000000000000000000 8
b00000000000000000000 9
b00000000000000000000 :
b00000000000000000000 ;
b00000000000000000000 <
b00000000000000000000 =
b00000000000000000000 >
b00000000000000000000 ?
b00000000000000000000 @
b00000000000000000000 A
b00000000000000000000 B
b00000000000000000000 C
b00000000000000000000 D
b00000000000000000000 E
b00000000000000000000 F
b00000000000000000000 G
0H
b0000000000000000000000000000000000000000000000000000000000000000 I
b0000000000000000000000000000000000000000000000000000000000000000 K
b0000000000000000000000000000000000000000000000000000000000000000 M
b0000000000000000000000000000000000000000000000000000000000000000 O
b0000000000000000000000000000000000000000000000000000000000000000 Q
b0000000000000000000000000000000000000000000000000000000000000000 S
b00000000000000000000000000010100 U
b0000000000000000000000000000000000000000000000000000000000000000 V
b0000000000000000000000000000000000000000000000010000000000000000 X
#5000
0#
06
#10000
1#
16
#15000
0#
06
#20000
1#
16
#25000
0#
06
#30000
1#
16
#35000
0#
06
#40000
1#
1$
b11111100011100010000 %
b00111000000110100000 &
b11000010011010010011 '
b00000000000100000000 (
b00001011100010000000 )
b01000011000000101101 *
b00111010001011001001 +
b00000000000100000000 ,
b00000000000001010101 -
b00000000000000111110 .
b00000000000001010010 /
b11100111000000100111 0
16
17
b11111100011100010000 8
b00111000000110100000 9
b11000010011010010011 :
b00000000000100000000 ;
b00001011100010000000 <
b01000011000000101101 =
b00111010001011001001 >
b00000000000100000000 ?
b00000000000001010101 @
b00000000000000111110 A
b00000000000001010010 B
b11100111000000100111 C
#45000
0#
06
#50000
1#
0$
b00000111000010011011 1
b00111111110000110010 2
b00010110100000101111 3
b00000000000100000000 4
15
16
07
b00000111000010011011 D
b00111111110000110010 E
b00010110100000101111 F
b00000000000100000000 G
1H
b1111111111111111111111111111111111111101111110101111111100100110 I
b0000000000000000000000000000000000000010111000000011100110100010 K
b0000000000000000000000000000000000000010000001010000000011011010 M
b0000000000000000000000000000000000000010111000000011100110100010 O
b0000000000000000000000000000000000000000000000001011001111000101 Q
b0000000000000000000000000000000000000000000000001011001111000101 S
#55000
0#
06
#60000
1#
1$
b11110100000111111101 %
b11010110011011001011 &
b10011111100001111110 '
b00001000000011110010 )
b00110011011011010101 *
b01011001100111000011 +
b00000000000011101011 -
b11111111111111101110 .
b00000000000010111010 /
b00010101001101011110 0
05
16
17
b11110100000111111101 8
b11010110011011001011 9
b10011111100001111110 :
b00001000000011110010 <
b00110011011011010101 =
b01011001100111000011 >
b00000000000011101011 @
b11111111111111101110 A
b00000000000010111010 B
b00010101001101011110 C
0H
#65000
0#
06
#70000
1#
0$
b11111011110101100100 1
b11111010011010000100 2
b11100111100001100111 3
15
16
07
b11111011110101100100 D
b11111010011010000100 E
b11100111100001100111 F
1H
b1111111111111111111111111111111111111100011100100100001010000101 I
b0000000000000000000000000000000000001001001011110101011001010101 K
b0000000000000000000000000000000000000011100011011011110101111011 M
b0000000000000000000000000000000000001001001011110101011001010101 O
b0000000000000000000000000000000000000000000000000110001100001100 Q
b0000000000000000000000000000000000000000000000000110001100001100 S
#75000
0#
06
#80000
1#
1$
b00010011101101101101 %
b01111111110011111111 &
b10100000010011101011 '
b01100011000111000111 )
b00010000010011001111 *
b01010100001011011001 +
b11111111111110011000 -
b11111111111100000110 .
b00000000000000101011 /
b01001011101110000100 0
05
16
17
b00010011101101101101 8
b01111111110011111111 9
b10100000010011101011 :
b01100011000111000111 <
b00010000010011001111 =
b01010100001011011001 >
b11111111111110011000 @
b11111111111100000110 A
b00000000000000101011 B
b01001011101110000100 C
0H
#85000
0#
06
#90000
1#
0$
b01001010000101100110 1
b00110011011100100001 2
b00011011011111001111 3
15
16
07
b01001010000101100110 D
b00110011011100100001 E
b00011011011111001111 F
1H
b1111111111111111111111111111111111111011011011010010001000101011 I
b0000000000000000000000000000000000000110101011011011000101001010 K
b0000000000000000000000000000000000000100100100101101110111010101 M
b0000000000000000000000000000000000000110101011011011000101001010 O
b0000000000000000000000000000000000000000000000001010111101010001 Q
b0000000000000000000000000000000000000000000000001010111101010001 S
#95000
0#
06
#100000
1#
1$
b00000001101011011100 %
b10100100011110000101 &
b00100011100110011100 '
b01001011010010001001 )
b01100110110001110001 *
b10010000011000101001 +
b00000000000001111011 -
b00000000000001001100 .
b11111111111101001001 /
b11011001111010011001 0
05
16
17
b00000001101011011100 8
b10100100011110000101 9
b00100011100110011100 :
b01001011010010001001 <
b01100110110001110001 =
b10010000011000101001 >
b00000000000001111011 @
b00000000000001001100 A
b11111111111101001001 B
b11011001111010011001 C
0H
#105000
0#
06
#110000
1#
0$
b00100011000011010001 1
b11111100100100011010 2
b11100000110110100110 3
15
16
07
b00100011000011010001 D
b11111100100100011010 E
b11100000110110100110 F
1H
b1111111111111111111111111111111111111010011000011000110110101100 I
b0000000000000000000000000000000000001100011001001001001101100100 K
b0000000000000000000000000000000000000101100111100111001001010100 M
b0000000000000000000000000000000000001100011001001001001101100100 O
b0000000000000000000000000000000000000000000000000111010000010010 Q
b0000000000000000000000000000000000000000000000000111010000010010 S
#115000
0#
06
#120000
1#
1$
b10010000001100011010 %
b11100000100100110100 &
b10001000110000111011 '
b11011011100100101001 )
b00001100110000100110 *
b10111101011000110011 +
b11111111111100010101 -
b00000000000001000101 .
b11111111111101011110 /
b10101001000011101101 0
05
16
17
b10010000001100011010 8
b11100000100100110100 9
b10001000110000111011 :
b11011011100100101001 <
b00001100110000100110 =
b10111101011000110011 >
b11111111111100010101 @
b00000000000001000101 A
b11111111111101011110 B
b10101001000011101101 C
0H
#125000
0#
06
#130000
1#
0$
b11010100111111010110 1
b00001000111001101001 2
b10111000110010101100 3
15
16
07
b11010100111111010110 D
b00001000111001101001 E
b10111000110010101100 F
1H
b0000000000000000000000000000000000000101001010101101000111010000 I
b1111111111111111111111111111111111111010010101101001110010000101 K
b1111111111111111111111111111111111111010110101010010111000110000 M
b1111111111111111111111111111111111111010010101101001110010000101 O
b0000000000000000000000000000000000000000000000001110100110100101 Q
b0000000000000000000000000000000000000000000000001110100110100101 S
#135000
0#
06
#140000
1#
1$
b01111111100011011011 %
b11101000110010010010 &
b11000100111100111100 '
b10101000000111111011 )
b01001101100111010001 *
b01000100001110011111 +
b11111111111100101010 -
b11111111111100010101 .
b00000000000011011111 /
b00010010111010010101 0
05
16
17
b01111111100011011011 8
b11101000110010010010 9
b11000100111100111100 :
b10101000000111111011 <
b01001101100111010001 =
b01000100001110011111 >
b11111111111100101010 @
b11111111111100010101 A
b00000000000011011111 B
b00010010111010010101 C
0H
#145000
0#
06
#150000
1#
0$
b11111111100110001001 1
b00100100101011000111 2
b00010000100011000110 3
15
16
07
b11111111100110001001 D
b00100100101011000111 E
b00010000100011000110 F
1H
b1111111111111111111111111111111111111000101000101000100100101100 I
b0000000000000000000000000000000000001100011001100101100010101000 K
b0000000000000000000000000000000000000111010111010111011011010100 M
b0000000000000000000000000000000000001100011001100101100010101000 O
b0000000000000000000000000000000000000000000000001001100000001110 Q
b0000000000000000000000000000000000000000000000001001100000001110 S
#155000
0#
06
#160000
1#
1$
b11110101110111100010 %
b00001100100000111000 &
b10000010000101100010 '
b11100000000111111111 )
b11010101110101111001 *
b11100011111000110001 +
b11111111111110000101 -
b00000000000010011100 .
b11111111111100001101 /
b11000100110010110011 0
05
16
17
b11110101110111100010 8
b00001100100000111000 9
b10000010000101100010 :
b11100000000111111111 <
b11010101110101111001 =
b11100011111000110001 >
b11111111111110000101 @
b00000000000010011100 A
b11111111111100001101 B
b11000100110010110011 C
0H
#165000
0#
06
#170000
1#
0$
b11101000001011111000 1
b11101010000111000111 2
b10111111101000001100 3
15
16
07
b11101000001011111000 D
b11101010000111000111 E
b10111111101000001100 F
1H
b0000000000000000000000000000000000000100100011001110100110000100 I
b1111111111111111111111111111111111111000110001001100000100110000 K
b1111111111111111111111111111111111111011011100110001011001111100 M
b1111111111111111111111111111111111111000110001001100000100110000 O
b0000000000000000000000000000000000000000000000001010000100010111 Q
b0000000000000000000000000000000000000000000000001010000100010111 S
#175000
0#
06
#180000
1#
1$
b11001101001110000110 %
b00100011111110000001 &
b00001000100001001000 '
b00000100101011101001 )
b00101001100000000001 *
b01100110111101011010 +
b00000000000000100001 -
b00000000000011101111 .
b00000000000000001011 /
b11010110011001100100 0
05
16
17
b11001101001110000110 8
b00100011111110000001 9
b00001000100001001000 :
b00000100101011101001 <
b00101001100000000001 =
b01100110111101011010 >
b00000000000000100001 @
b00000000000011101111 A
b00000000000000001011 B
b11010110011001100100 C
0H
#185000
0#
06
#190000
1#
0$
b11111101010100110011 1
b00101000110001000011 2
b01011010011011101010 3
15
16
07
b11111101010100110011 D
b00101000110001000011 E
b01011010011011101010 F
1H
b1111111111111111111111111111111111111111000111001100110011001101 I
b0000000000000000000000000000000000000001000001011111000100001001 K
b0000000000000000000000000000000000000000111000110011001100110011 M
b0000000000000000000000000000000000000001000001011111000100001001 O
b0000000000000000000000000000000000000000000000001101111000001011 Q
b0000000000000000000000000000000000000000000000001101111000001011 S
#195000
0#
06
#200000
1#
1$
b01000100000001111010 %
b10001100100100011100 &
b11101010001001000010 '
b00001010010000111101 )
b00001101101111110000 *
b10011011011101001000 +
b00000000000000100110 -
b11111111111101110101 .
b11111111111100000111 /
b10100011100101010001 0
05
16
17
b01000100000001111010 8
b10001100100100011100 9
b11101010001001000010 :
b00001010010000111101 <
b00001101101111110000 =
b10011011011101001000 >
b00000000000000100110 @
b11111111111101110101 A
b11111111111100000111 B
b10100011100101010001 C
0H
#205000
0#
06
#210000
1#
0$
b00011001001010101000 1
b11101100011011000100 2
b10101111110000001101 3
15
16
07
b00011001001010101000 D
b11101100011011000100 E
b10101111110000001101 F
1H
b0000000000000000000000000000000000000000000110011101111010110110 I
b1111111111111111111111111111111111111111110111010010001100000000 K
b1111111111111111111111111111111111111111111001100010000101001010 M
b1111111111111111111111111111111111111111110111010010001100000000 O
b0000000000000000000000000000000000000000000000001011110111110110 Q
b0000000000000000000000000000000000000000000000001011110111110110 S
#215000
0#
06
#220000
1#
1$
b11101101011001000110 %
b01010000001101111011 &
b10101100101100110011 '
b10101101111011001111 )
b01011010100010101110 *
b11001001101011011011 +
b11111111111101110001 -
b00000000000011101111 .
b11111111111101111000 /
b01100111011101010101 0
05
16
17
b11101101011001000110 8
b01010000001101111011 9
b10101100101100110011 :
b10101101111011001111 <
b01011010100010101110 =
b11001001101011011011 >
b11111111111101110001 @
b00000000000011101111 A
b11111111111101111000 B
b01100111011101010101 C
0H
#225000
0#
06
#230000
1#
0$
b11101101011001000110 1
b01010000001101111011 2
b10101100101100110011 3
15
16
07
b11101101011001000110 D
b01010000001101111011 E
b10101100101100110011 F
1H
b0000000000000000000000000000000000001110100011111111000010100011 I
b0000000000000000000000000000000000000001110110110010010011010110 K
b1111111111111111111111111111111111110001011100000000111101011101 M
b0000000000000000000000000000000000000001110110110010010011010110 O
b1111111111111111111111111111111111111111111110000010011101110010 Q
b0000000000000000000000000000000000000000000000000000000000000000 S
#235000
0#
06
#240000
1#
1$
b00101001001110001110 %
b10001001000110010010 &
b11101011110000010001 '
b10110001011011010001 )
b11001000100110010110 *
b01010000100000101110 +
b00000000000000010101 -
b11111111111111011101 .
b00000000000000100110 /
b11101111111101000111 0
05
16
17
b00101001001110001110 8
b10001001000110010010 9
b11101011110000010001 :
b10110001011011010001 <
b11001000100110010110 =
b01010000100000101110 >
b00000000000000010101 @
b11111111111111011101 A
b00000000000000100110 B
b11101111111101000111 C
0H
#245000
0#
06
#250000
1#
0$
b00010101011011000000 1
b10010011100110000000 2
b11111100011010000101 3
15
16
07
b00010101011011000000 D
b10010011100110000000 E
b11111100011010000101 F
1H
b0000000000000000000000000000000000000000000010010110010100110110 I
b1111111111111111111111111111111111111111110001110010100001000001 K
b1111111111111111111111111111111111111111111101101001101011001010 M
b1111111111111111111111111111111111111111110001110010100001000001 O
b0000000000000000000000000000000000000000000000000010101001010000 Q
b0000000000000000000000000000000000000000000000000010101001010000 S
#255000
0#
06
#260000
1#
1$
b00110111100000111111 %
b11010000001111100001 &
b00010001111010101111 '
b10001011111001011100 )
b00101000100100001000 *
b00010110000011011101 +
b11111111111100111011 -
b00000000000010000101 .
b00000000000000011010 /
b10100001111111111100 0
05
16
17
b00110111100000111111 8
b11010000001111100001 9
b00010001111010101111 :
b10001011111001011100 <
b00101000100100001000 =
b00010110000011011101 >
b11111111111100111011 @
b00000000000010000101 A
b00000000000000011010 B
b10100001111111111100 C
0H
#265000
0#
06
#270000
1#
0$
b10011101110110011110 1
b00011111010100110010 2
b00010101100111110000 3
15
16
07
b10011101110110011110 D
b00011111010100110010 E
b00010101100111110000 F
1H
b1111111111111111111111111111111111110110000001001001010100110000 I
b0000000000000000000000000000000000001011001001011111000110011110 K
b0000000000000000000000000000000000001001111110110110101011010000 M
b0000000000000000000000000000000000001011001001011111000110011110 O
b0000000000000000000000000000000000000000000000001110010100111000 Q
b0000000000000000000000000000000000000000000000001110010100111000 S
#275000
0#
06
#280000
1#
1$
b10111011111010111010 %
b11011000101010000000 &
b10111101110111111101 '
b11101010000011011001 )
b10101000000001101100 *
b00011101110110001100 +
b00000000000000000011 -
b11111111111100000100 .
b00000000000000100010 /
b11010101100011101110 0
05
16
17
b10111011111010111010 8
b11011000101010000000 9
b10111101110111111101 :
b11101010000011011001 <
b10101000000001101100 =
b00011101110110001100 >
b00000000000000000011 @
b11111111111100000100 A
b00000000000000100010 B
b11010101100011101110 C
0H
#285000
0#
06
#290000
1#
0$
b11000101111100100111 1
b11001110000101100011 2
b11010010101110111100 3
15
16
07
b11000101111100100111 D
b11001110000101100011 E
b11010010101110111100 F
1H
b1111111111111111111111111111111111111111001010110100111111001000 I
b0000000000000000000000000000000000000011110100101000001100001011 K
b0000000000000000000000000000000000000000110101001011000000111000 M
b0000000000000000000000000000000000000011110100101000001100001011 O
b0000000000000000000000000000000000000000000000000011011110100100 Q
b0000000000000000000000000000000000000000000000000011011110100100 S
#295000
0#
06
#300000
1#
1$
b01001010011000110111 %
b10100101111110111100 &
b00111110100010010011 '
b10011010101101110010 )
b01110101000010111100 *
b00110000101100110111 +
b11111111111110001000 -
b11111111111100101101 .
b00000000000011110011 /
b11101010100100000000 0
05
16
17
b01001010011000110111 8
b10100101111110111100 9
b00111110100010010011 :
b10011010101101110010 <
b01110101000010111100 =
b00110000101100110111 >
b11111111111110001000 @
b11111111111100101101 A
b00000000000011110011 B
b11101010100100000000 C
0H
#305000
0#
06
#310000
1#
0$
b11000100101000001110 1
b01000011101001001100 2
b00110100000000000111 3
15
16
07
b11000100101000001110 D
b01000011101001001100 E
b00110100000000000111 F
1H
b0000000000000000000000000000000000000100110100111111000111001101 I
b1111111111111111111111111111111111111001101010001100101100000100 K
b1111111111111111111111111111111111111011001011000000111000110011 M
b1111111111111111111111111111111111111001101010001100101100000100 O
b0000000000000000000000000000000000000000000000001100001011101100 Q
b0000000000000000000000000000000000000000000000001100001011101100 S
#315000
0#
06
#320000
1#
1$
b01100010100000010011 %
b01010111110010011001 &
b10111010101111000000 '
b00110111001110101011 )
b01110101110010110010 *
b10101101011101001100 +
b11111111111100110011 -
b11111111111111010011 .
b00000000000010011110 /
b01111101010010101001 0
05
16
17
b01100010100000010011 8
b01010111110010011001 9
b10111010101111000000 :
b00110111001110101011 <
b01110101110010110010 =
b10101101011101001100 >
b11111111111100110011 @
b11111111111111010011 A
b00000000000010011110 B
b01111101010010101001 C
0H
#325000
0#
06
#330000
1#
0$
b01001010011101011100 1
b01101000011101011001 2
b10110011010110110101 3
15
16
07
b01001010011101011100 D
b01101000011101011001 E
b10110011010110110101 F
1H
b1111111111111111111111111111111111111111010000111010101101100100 I
b0000000000000000000000000000000000000001010100101111001101001011 K
b0000000000000000000000000000000000000000101111000101010010011100 M
b0000000000000000000000000000000000000001010100101111001101001011 O
b0000000000000000000000000000000000000000000000001000111000111101 Q
b0000000000000000000000000000000000000000000000001000111000111101 S
#335000
0#
06
#340000
1#
1$
b10111101110101011000 %
b01011110010110110101 &
b01100011100000101101 '
b00110000001101110011 )
b11101000110011010100 *
b01001001000101110010 +
b11111111111100010001 -
b00000000000010100000 .
b11111111111111010010 /
b00011000001111101101 0
05
16
17
b10111101110101011000 8
b01011110010110110101 9
b01100011100000101101 :
b00110000001101110011 <
b11101000110011010100 =
b01001001000101110010 >
b11111111111100010001 @
b00000000000010100000 A
b11111111111111010010 B
b00011000001111101101 C
0H
#345000
0#
06
#350000
1#
0$
b00010000101011000001 1
b00001001001110000101 2
b01010000011000000101 3
15
16
07
b00010000101011000001 D
b00001001001110000101 E
b01010000011000000101 F
1H
b0000000000000000000000000000000000000111111100011100000011100010 I
b1111111111111111111111111111111111110101000001111101010111000101 K
b1111111111111111111111111111111111111000000011100011111100011110 M
b1111111111111111111111111111111111110101000001111101010111000101 O
b0000000000000000000000000000000000000000000000001011100101100111 Q
b0000000000000000000000000000000000000000000000001011100101100111 S
#355000
0#
06
#360000
1#
1$
b10011100010000100000 %
b11111011100110101111 &
b01100011011111110110 '
b11110010011011110100 )
b01011100100100010110 *
b11000110010010100100 +
b11111111111111010011 -
b11111111111111001010 .
b00000000000010000011 /
b11110000000000110100 0
05
16
17
b10011100010000100000 8
b11111011100110101111 9
b01100011011111110110 :
b11110010011011110100 <
b01011100100100010110 =
b11000110010010100100 >
b11111111111111010011 @
b11111111111111001010 A
b00000000000010000011 B
b11110000000000110100 C
0H
#365000
0#
06
#370000
1#
0$
b11000011111001101111 1
b00101000001101100010 2
b00011011001011010001 3
15
16
07
b11000011111001101111 D
b00101000001101100010 E
b00011011001011010001 F
1H
b0000000000000000000000000000000000000011010101100011001001011000 I
b1111111111111111111111111111111111111000101111110011111000001100 K
b1111111111111111111111111111111111111100101010011100110110101000 M
b1111111111111111111111111111111111111000101111110011111000001100 O
b0000000000000000000000000000000000000000000000000111010111000101 Q
b0000000000000000000000000000000000000000000000000111010111000101 S
#375000
0#
06
#380000
1#
1$
b10101001011110101011 %
b00011101011101110000 &
b10000000000100110001 '
b01011110010111000011 )
b00101111000011000011 *
b10011101100001100111 +
b00000000000000111110 -
b11111111111111010100 .
b00000000000001111111 /
b01000010100111101000 0
05
16
17
b10101001011110101011 8
b00011101011101110000 9
b10000000000100110001 :
b01011110010111000011 <
b00101111000011000011 =
b10011101100001100111 >
b00000000000000111110 @
b11111111111111010100 A
b00000000000001111111 B
b01000010100111101000 C
0H
#385000
0#
06
#390000
1#
0$
b11110100001000010010 1
b00100100101110001010 2
b10001100001110101001 3
15
16
07
b11110100001000010010 D
b00100100101110001010 E
b10001100001110101001 F
1H
b1111111111111111111111111111111111111110100100100011001101111001 I
b0000000000000000000000000000000000000011011101100101001101010110 K
b0000000000000000000000000000000000000001011011011100110010000111 M
b0000000000000000000000000000000000000011011101100101001101010110 O
b0000000000000000000000000000000000000000000000000110100110100111 Q
b0000000000000000000000000000000000000000000000000110100110100111 S
#395000
0#
06
#400000
1#
1$
b11000010001100010011 %
b01101011101011110100 &
b01110110101010100011 '
b10011110110101010101 )
b10001111110010001010 *
b00001000101001010000 +
b11111111111100100110 -
b11111111111100001111 .
b11111111111101000000 /
b01001100111011111101 0
05
16
17
b11000010001100010011 8
b01101011101011110100 9
b01110110101010100011 :
b10011110110101010101 <
b10001111110010001010 =
b00001000101001010000 >
b11111111111100100110 @
b11111111111100001111 A
b11111111111101000000 B
b01001100111011111101 C
0H
#405000
0#
06
#410000
1#
0$
b10111011011101110110 1
b01000001110110110001 2
b01100001101111001011 3
15
16
07
b10111011011101110110 D
b01000001110110110001 E
b01100001101111001011 F
1H
b1111111111111111111111111111111111111100001100110010010011011110 I
b0000000000000000000000000000000000010011111110100100001111010110 K
b0000000000000000000000000000000000000011110011001101101100100010 M
b0000000000000000000000000000000000010011111110100100001111010110 O
b0000000000000000000000000000000000000000000000000011000010110010 Q
b0000000000000000000000000000000000000000000000000011000010110010 S
#415000
0#
06
#420000
1#
1$
b11000101001000100001 %
b10110101111001100101 &
b01010110001110100010 '
b01100101011001100001 )
b00001101010010001110 *
b11010010000001100010 +
b00000000000011001011 -
b11111111111100111110 .
b11111111111101010011 /
b00001000100000101101 0
05
16
17
b11000101001000100001 8
b10110101111001100101 9
b01010110001110100010 :
b01100101011001100001 <
b00001101010010001110 =
b11010010000001100010 >
b00000000000011001011 @
b11111111111100111110 A
b11111111111101010011 B
b00001000100000101101 C
0H
#425000
0#
06
#430000
1#
0$
b11110000000111010100 1
b11001101010101011101 2
b00110010110001011000 3
15
16
07
b11110000000111010100 D
b11001101010101011101 E
b00110010110001011000 F
1H
b1111111111111111111111111111111111111101011110110111000000100111 I
b0000000000000000000000000000000000001001011000110100010111101110 K
b0000000000000000000000000000000000000010100001001000111111011001 M
b0000000000000000000000000000000000001001011000110100010111101110 O
b0000000000000000000000000000000000000000000000000100010010101000 Q
b0000000000000000000000000000000000000000000000000100010010101000 S
#435000
0#
06
#440000
1#
1$
b00111000000001111011 %
b10111001100011111100 &
b10001010011001000011 '
b11110001101101011100 )
b00111110101001111011 *
b10001001011011100101 +
b11111111111101110111 -
b11111111111100000100 .
b00000000000010010011 /
b01011000110100000011 0
05
16
17
b00111000000001111011 8
b10111001100011111100 9
b10001010011001000011 :
b11110001101101011100 <
b00111110101001111011 =
b10001001011011100101 >
b11111111111101110111 @
b11111111111100000100 A
b00000000000010010011 B
b01011000110100000011 C
0H
#445000
0#
06
#450000
1#
0$
b00001010101000111001 1
b00001111011110001110 2
b10001001110001010111 3
15
16
07
b00001010101000111001 D
b00001111011110001110 E
b10001001110001010111 F
1H
b0000000000000000000000000000000000000011110010100010000110010110 I
b1111111111111111111111111111111111111010001000010001000110011001 K
b1111111111111111111111111111111111111100001101011101111001101010 M
b1111111111111111111111111111111111111010001000010001000110011001 O
b0000000000000000000000000000000000000000000000001010010100111111 Q
b0000000000000000000000000000000000000000000000001010010100111111 S
#455000
0#
06
#460000
1#
1$
b00001100001101000000 %
b10010011000101001111 &
b10110001100000011110 '
b10101110000000001010 )
b11110001001111111011 *
b00100111100110010011 +
b11111111111101000111 -
b11111111111100000001 .
b00000000000010000011 /
b10110010100011010011 0
05
16
17
b00001100001101000000 8
b10010011000101001111 9
b10110001100000011110 :
b10101110000000001010 <
b11110001001111111011 =
b00100111100110010011 >
b11111111111101000111 @
b11111111111100000001 A
b00000000000010000011 B
b10110010100011010011 C
0H
#465000
0#
06
#470000
1#
0$
b11011011100000011101 1
b11000011110000101001 2
b11101110100011011001 3
15
16
07
b11011011100000011101 D
b11000011110000101001 E
b11101110100011011001 F
1H
b1111111111111111111111111111111111111110111000001111001101101001 I
b0000000000000000000000000000000000000010001010110100011110010001 K
b0000000000000000000000000000000000000001000111110000110010010111 M
b0000000000000000000000000000000000000010001010110100011110010001 O
b0000000000000000000000000000000000000000000000001000010001010110 Q
b0000000000000000000000000000000000000000000000001000010001010110 S
#475000
0#
06
#480000
1#
1$
b00000010010100000001 %
b01000011010101000100 &
b00000010110110101010 '
b10010010100010011011 )
b10011111011100010011 *
b01011000001011011010 +
b11111111111111000010 -
b11111111111110001011 .
b00000000000001010010 /
b10111001010011011001 0
05
16
17
b00000010010100000001 8
b01000011010101000100 9
b00000010110110101010 :
b10010010100010011011 <
b10011111011100010011 =
b01011000001011011010 >
b11111111111111000010 @
b11111111111110001011 A
b00000000000001010010 B
b10111001010011011001 C
0H
#485000
0#
06
#490000
1#
0$
b10101010111001111011 1
b11000011001010110111 2
b01000101100100111100 3
15
16
07
b10101010111001111011 D
b11000011001010110111 E
b01000101100100111100 F
1H
b1111111111111111111111111111111111111001101011100010101100100010 I
b0000000000000000000000000000000000001000000101001101011001111001 K
b0000000000000000000000000000000000000110010100011101010011011110 M
b0000000000000000000000000000000000001000000101001101011001111001 O
b0000000000000000000000000000000000000000000000001100100000110001 Q
b0000000000000000000000000000000000000000000000001100100000110001 S
#495000
0#
06
