rtl/core/preprocessing/intersection.sv
module intersection #(
    parameter WIDTH = 20  // 1 sign + 11 int + 8 frac = 20 bits, "12.8" format
)(
    input  logic                    clk_i,
    input  logic                    start_i,
    
    // Line segment endpoints (v1 to v2), each in 12.8 fixed point
    input  logic signed [WIDTH-1:0] v1_x,
    input  logic signed [WIDTH-1:0] v1_y,
    input  logic signed [WIDTH-1:0] v1_z,
    input  logic signed [WIDTH-1:0] v1_w,
    input  logic signed [WIDTH-1:0] v2_x,
    input  logic signed [WIDTH-1:0] v2_y,
    input  logic signed [WIDTH-1:0] v2_z,
    input  logic signed [WIDTH-1:0] v2_w,
    
    // Plane coefficients (a,b,c,d), each in 12.8 fixed point
    input  logic signed [WIDTH-1:0] plane_a,
    input  logic signed [WIDTH-1:0] plane_b,
    input  logic signed [WIDTH-1:0] plane_c,
    input  logic signed [WIDTH-1:0] plane_d,
    
    // Intersection point output in 12.8 fixed point (on segment)
    output logic signed [WIDTH-1:0] intersect_x,
    output logic signed [WIDTH-1:0] intersect_y,
    output logic signed [WIDTH-1:0] intersect_z,
    output logic signed [WIDTH-1:0] intersect_w,
    
    output logic                    done_o
);

always_ff @(posedge clk_i) begin
    if (start_i) begin
        // 64-bit accumulators to avoid overflow
        logic signed [63:0] sum_v1, sum_diff;
        logic signed [63:0] num, den;
        logic signed [63:0] t_raw;      // t in Q16, before clamping
        logic signed [63:0] t_clamped;  // t in Q16, clamped to [0,1]

        // For reference: 1.0 in Q16 is 65536
        localparam logic signed [63:0] Q16_ZERO = 64'd0;
        localparam logic signed [63:0] Q16_ONE  = 64'd65536;

        //====================
        //   plane . v1  (Q16)
        //====================
        sum_v1 = (plane_a * v1_x)
               + (plane_b * v1_y)
               + (plane_c * v1_z)
               + (plane_d * v1_w);

        // num = -(plane . v1)
        num = -sum_v1;  // Q16

        //==============================
        //   plane . (v2 - v1)  (Q16)
        //==============================
        sum_diff = (plane_a * (v2_x - v1_x))
                 + (plane_b * (v2_y - v1_y))
                 + (plane_c * (v2_z - v1_z))
                 + (plane_d * (v2_w - v1_w));
        den = sum_diff; // Q16

        //====================
        // Compute t = num / den in Q16
        // => t = (num << 16) / den
        //====================
        if (den == 0) begin
            // Degenerate: line parallel to plane => no intersection or infinite
            t_raw = 0;
        end
        else begin
            t_raw = (num <<< 16) / den;  
        end

        //====================
        // Clamp t to [0, 1] in Q16
        //====================
        if (t_raw < Q16_ZERO) begin
            t_clamped = Q16_ZERO;  // means intersection is effectively at v1
        end
        else if (t_raw > Q16_ONE) begin
            t_clamped = Q16_ONE;   // means intersection is effectively at v2
        end
        else begin
            t_clamped = t_raw;
        end

        //=========================================
        // Intersection in Q8 (clamped to segment):
        //   intersect = v1 + [t_clamped * (v2 - v1) >> 16]
        //=========================================
        intersect_x <= v1_x + ((t_clamped * (v2_x - v1_x)) >>> 16);
        intersect_y <= v1_y + ((t_clamped * (v2_y - v1_y)) >>> 16);
        intersect_z <= v1_z + ((t_clamped * (v2_z - v1_z)) >>> 16);
        intersect_w <= v1_w + ((t_clamped * (v2_w - v1_w)) >>> 16);

        done_o <= 1'b1;
    end
    else begin
        done_o <= 1'b0;
    end
end

endmodule

tb/test/core/preprocessing/dump.vcd
$version Generated by VerilatedVcd $end
$timescale 1ps $end
 $var wire 1 # clk_i $end
 $var wire 1 $ start_i $end
 $var wire 20 % v1_x [19:0] $end
 $var wire 20 & v1_y [19:0] $end
 $var wire 20 ' v1_z [19:0] $end
 $var wire 20 ( v1_w [19:0] $end
 $var wire 20 ) v2_x [19:0] $end
 $var wire 20 * v2_y [19:0] $end
 $var wire 20 + v2_z [19:0] $end
 $var wire 20 , v2_w [19:0] $end
 $var wire 20 - plane_a [19:0] $end
 $var wire 20 . plane_b [19:0] $end
 $var wire 20 / plane_c [19:0] $end
 $var wire 20 0 plane_d [19:0] $end
 $var wire 20 1 intersect_x [19:0] $end
 $var wire 20 2 intersect_y [19:0] $end
 $var wire 20 3 intersect_z [19:0] $end
 $var wire 20 4 intersect_w [19:0] $end
 $var wire 1 5 done_o $end
 $scope module intersection $end
  $var wire 32 U WIDTH [31:0] $end
  $var wire 1 6 clk_i $end
  $var wire 1 7 start_i $end
  $var wire 20 8 v1_x [19:0] $end
  $var wire 20 9 v1_y [19:0] $end
  $var wire 20 : v1_z [19:0] $end
  $var wire 20 ; v1_w [19:0] $end
  $var wire 20 < v2_x [19:0] $end
  $var wire 20 = v2_y [19:0] $end
  $var wire 20 > v2_z [19:0] $end
  $var wire 20 ? v2_w [19:0] $end
  $var wire 20 @ plane_a [19:0] $end
  $var wire 20 A plane_b [19:0] $end
  $var wire 20 B plane_c [19:0] $end
  $var wire 20 C plane_d [19:0] $end
  $var wire 20 D intersect_x [19:0] $end
  $var wire 20 E intersect_y [19:0] $end
  $var wire 20 F intersect_z [19:0] $end
  $var wire 20 G intersect_w [19:0] $end
  $var wire 1 H done_o $end
  $scope module unnamedblk1 $end
   $var wire 64 I sum_v1 [63:0] $end
   $var wire 64 K sum_diff [63:0] $end
   $var wire 64 M num [63:0] $end
   $var wire 64 O den [63:0] $end
   $var wire 64 Q t_raw [63:0] $end
   $var wire 64 S t_clamped [63:0] $end
   $var wire 64 V Q16_ZERO [63:0] $end
   $var wire 64 X Q16_ONE [63:0] $end
  $upscope $end
 $upscope $end
$enddefinitions $end


#0
1#
0$
b00000000000000000000 %
b00000000000000000000 &
b00000000000000000000 '
b00000000000000000000 (
b00000000000000000000 )
b00000000000000000000 *
b00000000000000000000 +
b00000000000000000000 ,
b00000000000000000000 -
b00000000000000000000 .
b00000000000000000000 /
b00000000000000000000 0
b00000000000000000000 1
b00000000000000000000 2
b00000000000000000000 3
b00000000000000000000 4
05
16
07
b00000000000000000000 8
b00000000000000000000 9
b00000000000000000000 :
b00000000000000000000 ;
b00000000000000000000 <
b00000000000000000000 =
b00000000000000000000 >
b00000000000000000000 ?
b00000000000000000000 @
b00000000000000000000 A
b00000000000000000000 B
b00000000000000000000 C
b00000000000000000000 D
b00000000000000000000 E
b00000000000000000000 F
b00000000000000000000 G
0H
b0000000000000000000000000000000000000000000000000000000000000000 I
b0000000000000000000000000000000000000000000000000000000000000000 K
b0000000000000000000000000000000000000000000000000000000000000000 M
b0000000000000000000000000000000000000000000000000000000000000000 O
b0000000000000000000000000000000000000000000000000000000000000000 Q
b0000000000000000000000000000000000000000000000000000000000000000 S
b00000000000000000000000000010100 U
b0000000000000000000000000000000000000000000000000000000000000000 V
b0000000000000000000000000000000000000000000000010000000000000000 X
#5000
0#
06
#10000
1#
16
#15000
0#
06
#20000
1#
16
#25000
0#
06
#30000
1#
16
#35000
0#
06
#40000
1#
1$
b10110110001000111110 %
b01100001111101111100 &
b00010001001110101011 '
b00000000000100000000 (
b00001100101111011001 )
b01010010010011010001 *
b11101101010111110101 +
b00000000000100000000 ,
b00000000000000001011 -
b00000000000000001010 .
b00000000000011111111 /
b00000011001011011101 0
16
17
b10110110001000111110 8
b01100001111101111100 9
b00010001001110101011 :
b00000000000100000000 ;
b00001100101111011001 <
b01010010010011010001 =
b11101101010111110101 >
b00000000000100000000 ?
b00000000000000001011 @
b00000000000000001010 A
b00000000000011111111 B
b00000011001011011101 C
#45000
0#
06
#50000
1#
0$
b11101101111001010101 1
b01010111111000011000 2
b11111010001001001011 3
b00000000000100000000 4
15
16
07
b11101101111001010101 D
b01010111111000011000 E
b11111010001001001011 F
b00000000000100000000 G
1H
b0000000000000000000000000000000000000001010011111110011111010111 I
b1111111111111111111111111111111111111101111101100100011010110001 K
b1111111111111111111111111111111111111110101100000001100000101001 M
b1111111111111111111111111111111111111101111101100100011010110001 O
b0000000000000000000000000000000000000000000000001010010011010010 Q
b0000000000000000000000000000000000000000000000001010010011010010 S
#55000
0#
06
#60000
1#
1$
b00100101000110101100 %
b00001000000010000100 &
b01010010100101000100 '
b10101010111100101000 )
b11001101000010010111 *
b11011010010000001001 +
b11111111111100101010 -
b00000000000000011111 .
b00000000000010111100 /
b11011110011100011100 0
05
16
17
b00100101000110101100 8
b00001000000010000100 9
b01010010100101000100 :
b10101010111100101000 <
b11001101000010010111 =
b11011010010000001001 >
b11111111111100101010 @
b00000000000000011111 A
b00000000000010111100 B
b11011110011100011100 C
0H
#65000
0#
06
#70000
1#
0$
b11101110011100101111 1
b11101101101000101111 2
b00011100101111100001 3
15
16
07
b11101110011100101111 D
b11101101101000101111 E
b00011100101111100001 F
1H
b1111111111111111111111111111111111111111110100001011010000100100 I
b0000000000000000000000000000000000000000011010011011010101010001 K
b0000000000000000000000000000000000000000001011110100101111011100 M
b0000000000000000000000000000000000000000011010011011010101010001 O
b0000000000000000000000000000000000000000000000000111001010001010 Q
b0000000000000000000000000000000000000000000000000111001010001010 S
#75000
0#
06
#80000
1#
1$
b00000011001111100001 %
b10010110100010101100 &
b11010110110100110111 '
b00110101100101001100 )
b01110100000010111011 *
b10000100101011110000 +
b00000000000001110001 -
b00000000000011100001 .
b11111111111101100111 /
b10000000101111010100 0
05
16
17
b00000011001111100001 8
b10010110100010101100 9
b11010110110100110111 :
b00110101100101001100 <
b01110100000010111011 =
b10000100101011110000 >
b00000000000001110001 @
b00000000000011100001 A
b11111111111101100111 B
b10000000101111010100 C
0H
#85000
0#
06
#90000
1#
0$
b00100111111100000100 1
b00111000000001000000 2
b10011010111100011111 3
15
16
07
b00100111111100000100 D
b00111000000001000000 E
b10011010111100011111 F
1H
b1111111111111111111111111111111111110011111000010111001110011110 I
b0000000000000000000000000000000000010000100111111110010111011001 K
b0000000000000000000000000000000000001100000111101000110001100010 M
b0000000000000000000000000000000000010000100111111110010111011001 O
b0000000000000000000000000000000000000000000000001011101010011111 Q
b0000000000000000000000000000000000000000000000001011101010011111 S
#95000
0#
06
#100000
1#
1$
b11000101010010001101 %
b11000001000100011000 &
b11100010111111011000 '
b11110100111100000001 )
b00000001000001111010 *
b11101101101100001011 +
b11111111111110101000 -
b11111111111111010001 .
b00000000000001000111 /
b11110010101101000011 0
05
16
17
b11000101010010001101 8
b11000001000100011000 9
b11100010111111011000 :
b11110100111100000001 <
b00000001000001111010 =
b11101101101100001011 >
b11111111111110101000 @
b11111111111111010001 A
b00000000000001000111 B
b11110010101101000011 C
0H
#105000
0#
06
#110000
1#
0$
b11011000111110100000 1
b11011011011111111110 2
b11100111011010010111 3
15
16
07
b11011000111110100000 D
b11011011011111111110 E
b11100111011010010111 F
1H
b0000000000000000000000000000000000000000101001100101010000001000 I
b1111111111111111111111111111111111111110011011011000000001000111 K
b1111111111111111111111111111111111111111010110011010101111111000 M
b1111111111111111111111111111111111111110011011011000000001000111 O
b0000000000000000000000000000000000000000000000000110100111001010 Q
b0000000000000000000000000000000000000000000000000110100111001010 S
#115000
0#
06
#120000
1#
1$
b00101011110010011001 %
b10111001101000110110 &
b01000010001110010111 '
b01001011000010110111 )
b11110011010101100001 *
b01010110110000001111 +
b11111111111111101000 -
b11111111111110101100 .
b00000000000001011101 /
b11011100000001100101 0
05
16
17
b00101011110010011001 8
b10111001101000110110 9
b01000010001110010111 :
b01001011000010110111 <
b11110011010101100001 =
b01010110110000001111 >
b11111111111111101000 @
b11111111111110101100 A
b00000000000001011101 B
b11011100000001100101 C
0H
#125000
0#
06
#130000
1#
0$
b00111011000111100011 1
b11010101111011111101 2
b01001100010010110001 3
15
16
07
b00111011000111100011 D
b11010101111011111101 E
b01001100010010110001 F
1H
b0000000000000000000000000000000000000000011100010000101011001011 I
b1111111111111111111111111111111111111111000110011000011010101100 K
b1111111111111111111111111111111111111111100011101111010100110101 M
b1111111111111111111111111111111111111111000110011000011010101100 O
b0000000000000000000000000000000000000000000000000111110110001111 Q
b0000000000000000000000000000000000000000000000000111110110001111 S
#135000
0#
06
#140000
1#
1$
b10111011001001111000 %
b00010110010110101100 &
b11110100101111011011 '
b00101010010000010010 )
b01100001001100111100 *
b01011101011111101011 +
b00000000000010110100 -
b11111111111111111101 .
b00000000000001101001 /
b00010110010011010111 0
05
16
17
b10111011001001111000 8
b00010110010110101100 9
b11110100101111011011 :
b00101010010000010010 <
b01100001001100111100 =
b01011101011111101011 >
b00000000000010110100 @
b11111111111111111101 A
b00000000000001101001 B
b00010110010011010111 C
0H
#145000
0#
06
#150000
1#
0$
b11010111110010100101 1
b00101001101001011000 2
b00001111101111011100 3
15
16
07
b11010111110010100101 D
b00101001101001011000 E
b00001111101111011100 F
1H
b1111111111111111111111111111111111111110000100000011111100101111 I
b0000000000000000000000000000000000000111100000110100101000101000 K
b0000000000000000000000000000000000000001111011111100000011010001 M
b0000000000000000000000000000000000000111100000110100101000101000 O
b0000000000000000000000000000000000000000000000000100000111111100 Q
b0000000000000000000000000000000000000000000000000100000111111100 S
#155000
0#
06
#160000
1#
1$
b10001101100100000010 %
b10001100101010010001 &
b10000011110001111110 '
b10111100101010010101 )
b00010000011110100010 *
b00010000011111011000 +
b11111111111100000111 -
b00000000000010011001 .
b11111111111110011011 /
b10100110000100011001 0
05
16
17
b10001101100100000010 8
b10001100101010010001 9
b10000011110001111110 :
b10111100101010010101 <
b00010000011110100010 =
b00010000011111011000 >
b11111111111100000111 @
b00000000000010011001 A
b11111111111110011011 B
b10100110000100011001 C
0H
#165000
0#
06
#170000
1#
0$
b10010000100110000101 1
b10010101001001010111 2
b10001100110101101101 3
15
16
07
b10010000100110000101 D
b10010101001001010111 E
b10001100110101101101 F
1H
b0000000000000000000000000000000000000000000101110011100100000001 I
b1111111111111111111111111111111111111110100101110100110010101100 K
b1111111111111111111111111111111111111111111010001100011011111111 M
b1111111111111111111111111111111111111110100101110100110010101100 O
b0000000000000000000000000000000000000000000000000001000001111011 Q
b0000000000000000000000000000000000000000000000000001000001111011 S
#175000
0#
06
#180000
1#
1$
b00101001001010001000 %
b10100010111100100001 &
b01010100100000001001 '
b00001010111110000101 )
b00011000111000000010 *
b11011100010010101111 +
b00000000000000010011 -
b11111111111111110000 .
b11111111111101000011 /
b00010010101101110010 0
05
16
17
b00101001001010001000 8
b10100010111100100001 9
b01010100100000001001 :
b00001010111110000101 <
b00011000111000000010 =
b11011100010010101111 >
b00000000000000010011 @
b11111111111111110000 A
b11111111111101000011 B
b00010010101101110010 C
0H
#185000
0#
06
#190000
1#
0$
b00011011111000100001 1
b11010110110011011110 2
b00011111101001000001 3
15
16
07
b00011011111000100001 D
b11010110110011011110 E
b00011111101001000001 F
1H
b1111111111111111111111111111111111111101110100110011000101100011 I
b0000000000000000000000000000000000000100111100100011001000101001 K
b0000000000000000000000000000000000000010001011001100111010011101 M
b0000000000000000000000000000000000000100111100100011001000101001 O
b0000000000000000000000000000000000000000000000000111000010010011 Q
b0000000000000000000000000000000000000000000000000111000010010011 S
#195000
0#
06
#200000
1#
1$
b00011111110110100010 %
b10100000111000100110 &
b01001110001110100111 '
b11011010000011111101 )
b00110110100101001101 *
b10000100110001101011 +
b00000000000001111111 -
b11111111111100010101 .
b11111111111110001001 /
b11001010110001000111 0
05
16
17
b00011111110110100010 8
b10100000111000100110 9
b01001110001110100111 :
b11011010000011111101 <
b00110110100101001101 =
b10000100110001101011 >
b00000000000001111111 @
b11111111111100010101 A
b11111111111110001001 B
b11001010110001000111 C
0H
#205000
0#
06
#210000
1#
0$
b00010011110100011000 1
b10111010101100100001 2
b00101011011111100011 3
15
16
07
b00010011110100011000 D
b10111010101100100001 E
b00101011011111100011 F
1H
b0000000000000000000000000000000000000000110110000100101011011011 I
b1111111111111111111111111111111111111011000110011010101000111100 K
b1111111111111111111111111111111111111111001001111011010100100101 M
b1111111111111111111111111111111111111011000110011010101000111100 O
b0000000000000000000000000000000000000000000000000010110000100100 Q
b0000000000000000000000000000000000000000000000000010110000100100 S
#215000
0#
06
#220000
1#
1$
b01100111010100101110 %
b00011001100101110100 &
b11111111011110010101 '
b01011010001111111001 )
b01111011110000010111 *
b01010110111010100110 +
b00000000000010111010 -
b11111111111111010111 .
b11111111111100010010 /
b00010000001111001000 0
05
16
17
b01100111010100101110 8
b00011001100101110100 9
b11111111011110010101 :
b01011010001111111001 <
b01111011110000010111 =
b01010110111010100110 >
b00000000000010111010 @
b11111111111111010111 A
b11111111111100010010 B
b00010000001111001000 C
0H
#225000
0#
06
#230000
1#
0$
b01011100100011101110 1
b01101010011010011100 2
b01000111011101111011 3
15
16
07
b01011100100011101110 D
b01101010011010011100 E
b01000111011101111011 F
1H
b0000000000000000000000000000000000000101011110110010101101010010 I
b1111111111111111111111111111111111111001010101111100000110010101 K
b1111111111111111111111111111111111111010100001001101010010101110 M
b1111111111111111111111111111111111111001010101111100000110010101 O
b0000000000000000000000000000000000000000000000001101001011000110 Q
b0000000000000000000000000000000000000000000000001101001011000110 S
#235000
0#
06
#240000
1#
1$
b00000001010000000111 %
b00001011100000011101 &
b11110101111000010011 '
b01010110100111000101 )
b00011110010101011011 *
b11001100011010100110 +
b11111111111101010100 -
b11111111111110001000 .
b00000000000001110111 /
b00010111111001010110 0
05
16
17
b00000001010000000111 8
b00001011100000011101 9
b11110101111000010011 :
b01010110100111000101 <
b00011110010101011011 =
b11001100011010100110 >
b11111111111101010100 @
b11111111111110001000 A
b00000000000001110111 B
b00010111111001010110 C
0H
#245000
0#
06
#250000
1#
0$
b00001110001100011100 1
b00001110010111001010 2
b11101111100101111011 3
15
16
07
b00001110001100011100 D
b00001110010111001010 E
b11101111100101111011 F
1H
b0000000000000000000000000000000000000000110011110100111010001001 I
b1111111111111111111111111111111111111010101010001100101110011101 K
b1111111111111111111111111111111111111111001100001011000101110111 M
b1111111111111111111111111111111111111010101010001100101110011101 O
b0000000000000000000000000000000000000000000000000010011011010001 Q
b0000000000000000000000000000000000000000000000000010011011010001 S
#255000
0#
06
#260000
1#
1$
b01010000011101100101 %
b10111001110000010110 &
b10101100110010011000 '
b11110011001001000100 )
b00111011011001001000 *
b01101100100100011100 +
b00000000000010101011 -
b00000000000011111111 .
b11111111111100100111 /
b11100011010100101111 0
05
16
17
b01010000011101100101 8
b10111001110000010110 9
b10101100110010011000 :
b11110011001001000100 <
b00111011011001001000 =
b01101100100100011100 >
b00000000000010101011 @
b00000000000011111111 A
b11111111111100100111 B
b11100011010100101111 C
0H
#265000
0#
06
#270000
1#
0$
b00110111011110111010 1
b11011100011101001000 2
b11100000000111110001 3
15
16
07
b00110111011110111010 D
b11011100011101001000 E
b11100000000111110001 F
1H
b0000000000000000000000000000000000000001100110100010110010001001 I
b1111111111111111111111111111111111111010000000111010111011011111 K
b1111111111111111111111111111111111111110011001011101001101110111 M
b1111111111111111111111111111111111111010000000111010111011011111 O
b0000000000000000000000000000000000000000000000000100010010000110 Q
b0000000000000000000000000000000000000000000000000100010010000110 S
#275000
0#
06
#280000
1#
1$
b11101000000111001011 %
b01001000011101010101 &
b00010100011100001100 '
b00011011011010110011 )
b00111011011101100000 *
b01110010111110100110 +
b00000000000011011110 -
b00000000000001001000 .
b11111111111110110100 /
b11111111011001010011 0
05
16
17
b11101000000111001011 8
b01001000011101010101 9
b00010100011100001100 :
b00011011011010110011 <
b00111011011101100000 =
b01110010111110100110 >
b00000000000011011110 @
b00000000000001001000 A
b11111111111110110100 B
b11111111011001010011 C
0H
#285000
0#
06
#290000
1#
0$
b00000100010001010111 1
b01000001010100110010 2
b01001000010100111010 3
15
16
07
b00000100010001010111 D
b01000001010100110010 E
b01001000010100111010 F
1H
b1111111111111111111111111111111111111111100011111101100101100010 I
b0000000000000000000000000000000000000000110011000101011010010000 K
b0000000000000000000000000000000000000000011100000010011010011110 M
b0000000000000000000000000000000000000000110011000101011010010000 O
b0000000000000000000000000000000000000000000000001000110010000001 Q
b0000000000000000000000000000000000000000000000001000110010000001 S
#295000
0#
06
#300000
1#
1$
b10011001111100010010 %
b00000110111111101001 &
b10000011110010000011 '
b11101010000110101100 )
b10001000001110011101 *
b01101110100000001001 +
b00000000000011101110 -
b00000000000001100100 .
b11111111111100101011 /
b11111111001011001001 0
05
16
17
b10011001111100010010 8
b00000110111111101001 9
b10000011110010000011 :
b11101010000110101100 <
b10001000001110011101 =
b01101110100000001001 >
b00000000000011101110 @
b00000000000001100100 A
b11111111111100101011 B
b11111111001011001001 C
0H
#305000
0#
06
#310000
1#
0$
b10011110110100110111 1
b11111111010001010100 2
b10010010000101010100 3
15
16
07
b10011110110100110111 D
b11111111010001010100 E
b10010010000101010100 F
1H
b0000000000000000000000000000000000000000101001100000100111000001 I
b1111111111111111111111111111111111110101010110110110011011111110 K
b1111111111111111111111111111111111111111010110011111011000111111 M
b1111111111111111111111111111111111110101010110110110011011111110 O
b0000000000000000000000000000000000000000000000000000111110011001 Q
b0000000000000000000000000000000000000000000000000000111110011001 S
#315000
0#
06
#320000
1#
1$
b00010110011101101000 %
b01011101101111011010 &
b00001100001110000101 '
b10100110001011000111 )
b11110101110100110101 *
b10010010100001010111 +
b00000000000010110010 -
b11111111111101101100 .
b00000000000010101100 /
b00111100101111001001 0
05
16
17
b00010110011101101000 8
b01011101101111011010 9
b00001100001110000101 :
b10100110001011000111 <
b11110101110100110101 =
b10010010100001010111 >
b00000000000010110010 @
b11111111111101101100 A
b00000000000010101100 B
b00111100101111001001 C
0H
#325000
0#
06
#330000
1#
0$
b11110100010001110110 1
b00111110000110110010 2
b11100111001010111110 3
15
16
07
b11110100010001110110 D
b00111110000110110010 E
b11100111001010111110 F
1H
b0000000000000000000000000000000000000001111001011111001010100100 I
b1111111111111111111111111111111111111001110000111011110010001010 K
b1111111111111111111111111111111111111110000110100000110101011100 M
b1111111111111111111111111111111111111001110000111011110010001010 O
b0000000000000000000000000000000000000000000000000100110111101111 Q
b0000000000000000000000000000000000000000000000000100110111101111 S
#335000
0#
06
#340000
1#
1$
b01010010110111100010 %
b00001101100100110101 &
b01011011001110000110 '
b10100011100101101110 )
b00011010011101110111 *
b11000000010011001001 +
b00000000000000001011 -
b11111111111111100010 .
b11111111111101100111 /
b00011010100110001100 0
05
16
17
b01010010110111100010 8
b00001101100100110101 9
b01011011001110000110 :
b10100011100101101110 <
b00011010011101110111 =
b11000000010011001001 >
b00000000000000001011 @
b11111111111111100010 A
b11111111111101100111 B
b00011010100110001100 C
0H
#345000
0#
06
#350000
1#
0$
b00011100011011000001 1
b00010001100101000110 2
b00101011000110010001 3
15
16
07
b00011100011011000001 D
b00010001100101000110 E
b00101011000110010001 F
1H
b1111111111111111111111111111111111111110011000001100010101101010 I
b0000000000000000000000000000000000000101001110001100001000111101 K
b0000000000000000000000000000000000000001100111110011101010010110 M
b0000000000000000000000000000000000000101001110001100001000111101 O
b0000000000000000000000000000000000000000000000000100111110000101 Q
b0000000000000000000000000000000000000000000000000100111110000101 S
#355000
0#
06
#360000
1#
1$
b01111001101000001010 %
b11101110011101011001 &
b11101010010000101011 '
b01001000000010101101 )
b00100011011110111100 *
b01011001111001101000 +
b00000000000010000100 -
b00000000000010110000 .
b00000000000000100011 /
b11001110110001001100 0
05
16
17
b01111001101000001010 8
b11101110011101011001 9
b11101010010000101011 :
b01001000000010101101 <
b00100011011110111100 =
b01011001111001101000 >
b00000000000010000100 @
b00000000000010110000 A
b00000000000000100011 B
b11001110110001001100 C
0H
#365000
0#
06
#370000
1#
0$
b01110110101100001110 1
b11110001100110010110 2
b11110000110111110010 3
15
16
07
b01110110101100001110 D
b11110001100110010110 E
b11110000110111110010 F
1H
b1111111111111111111111111111111111111111111001110011100000111001 I
b0000000000000000000000000000000000000001101000100110011001110011 K
b0000000000000000000000000000000000000000000110001100011111000111 M
b0000000000000000000000000000000000000001101000100110011001110011 O
b0000000000000000000000000000000000000000000000000000111100101001 Q
b0000000000000000000000000000000000000000000000000000111100101001 S
#375000
0#
06
#380000
1#
1$
b00110111011111100111 %
b01010101010111100001 &
b10001110010110000000 '
b11001101111000100010 )
b11001000110001000110 *
b00110000001110000111 +
b00000000000011100110 -
b00000000000011001001 .
b00000000000011110010 /
b00010111010101011000 0
05
16
17
b00110111011111100111 8
b01010101010111100001 9
b10001110010110000000 :
b11001101111000100010 <
b11001000110001000110 =
b00110000001110000111 >
b00000000000011100110 @
b00000000000011001001 A
b00000000000011110010 B
b00010111010101011000 C
0H
#385000
0#
06
#390000
1#
0$
b11110101001111110100 1
b11111101001011000010 2
b11110011111000100111 3
15
16
07
b11110101001111110100 D
b11111101001011000010 E
b11110011111000100111 F
1H
b0000000000000000000000000000000000000010000011000111001000110011 I
b1111111111111111111111111111111111111100101110111111000011101101 K
b1111111111111111111111111111111111111101111100111000110111001101 M
b1111111111111111111111111111111111111100101110111111000011101101 O
b0000000000000000000000000000000000000000000000001010000010010101 Q
b0000000000000000000000000000000000000000000000001010000010010101 S
#395000
0#
06
#400000
1#
1$
b00001010011111101110 %
b01100100001111001011 &
b11010011101000011100 '
b01010111100110010010 )
b00111011100010000111 *
b01001111110001001011 +
b11111111111101100110 -
b11111111111100001001 .
b00000000000000011111 /
b01101100000100100110 0
05
16
17
b00001010011111101110 8
b01100100001111001011 9
b11010011101000011100 :
b01010111100110010010 <
b00111011100010000111 =
b01001111110001001011 >
b11111111111101100110 @
b11111111111100001001 A
b00000000000000011111 B
b01101100000100100110 C
0H
#405000
0#
06
#410000
1#
0$
b00001101101011110110 1
b01100010100011011010 2
b11011000110001000101 3
15
16
07
b00001101101011110110 D
b01100010100011011010 E
b11011000110001000101 F
1H
b1111111111111111111111111111111111111111111110101100000101011011 I
b0000000000000000000000000000000000000000011111101100010110100101 K
b0000000000000000000000000000000000000000000001010011111010100101 M
b0000000000000000000000000000000000000000011111101100010110100101 O
b0000000000000000000000000000000000000000000000000000101010010111 Q
b0000000000000000000000000000000000000000000000000000101010010111 S
#415000
0#
06
#420000
1#
1$
b01101100100010011010 %
b01010000110101000010 &
b01001000001000001101 '
b01101110011010000111 )
b00101111011001011100 *
b00100001100100000111 +
b11111111111101100010 -
b00000000000001011001 .
b00000000000001111100 /
b00100010000110011101 0
05
16
17
b01101100100010011010 8
b01010000110101000010 9
b01001000001000001101 :
b01101110011010000111 <
b00101111011001011100 =
b00100001100100000111 >
b11111111111101100010 @
b00000000000001011001 A
b00000000000001111100 B
b00100010000110011101 C
0H
#425000
0#
06
#430000
1#
0$
b01101110010101001000 1
b00110000110010010001 2
b00100011001010100101 3
15
16
07
b01101110010101001000 D
b00110000110010010001 E
b00100011001010100101 F
1H
b0000000000000000000000000000000000000001111000100110100000110010 I
b1111111111111111111111111111111111111110000010001011001011011100 K
b1111111111111111111111111111111111111110000111011001011111001110 M
b1111111111111111111111111111111111111110000010001011001011011100 O
b0000000000000000000000000000000000000000000000001111010101011111 Q
b0000000000000000000000000000000000000000000000001111010101011111 S
#435000
0#
06
#440000
1#
1$
b00111010100100110101 %
b00001000010111100001 &
b00010100101110001100 '
b11001110110100010110 )
b00001000100101110011 *
b01110111010011001010 +
b00000000000010111001 -
b11111111111111010101 .
b00000000000001001111 /
b11010101110010110100 0
05
16
17
b00111010100100110101 8
b00001000010111100001 9
b00010100101110001100 :
b11001110110100010110 <
b00001000100101110011 =
b01110111010011001010 >
b00000000000010111001 @
b11111111111111010101 A
b00000000000001001111 B
b11010101110010110100 C
0H
#445000
0#
06
#450000
1#
0$
b00101110111110010011 1
b00001000011001000011 2
b00011111010101011100 3
15
16
07
b00101110111110010011 D
b00001000011001000011 E
b00011111010101011100 F
1H
b0000000000000000000000000000000000000000010100011100111010110110 I
b1111111111111111111111111111111111111101000010000010111000110101 K
b1111111111111111111111111111111111111111101011100011000101001010 M
b1111111111111111111111111111111111111101000010000010111000110101 O
b0000000000000000000000000000000000000000000000000001101110010000 Q
b0000000000000000000000000000000000000000000000000001101110010000 S
#455000
0#
06
#460000
1#
1$
b10010011011000011010 %
b10001000011000100101 &
b01001010111100001101 '
b11101001000001001010 )
b10101110010110001010 *
b00100110010101011010 +
b11111111111111111010 -
b11111111111110100011 .
b00000000000010010110 /
b10111011100111010010 0
05
16
17
b10010011011000011010 8
b10001000011000100101 9
b01001010111100001101 :
b11101001000001001010 <
b10101110010110001010 =
b00100110010101011010 >
b11111111111111111010 @
b11111111111110100011 A
b00000000000010010110 B
b10111011100111010010 C
0H
#465000
0#
06
#470000
1#
0$
b11000100110111100010 1
b10011110010100100011 2
b00110101110010011000 3
15
16
07
b11000100110111100010 D
b10011110010100100011 E
b00110101110010011000 F
1H
b0000000000000000000000000000000000000001010110000110001110010001 I
b1111111111111111111111111111111111111101101011000000110001001101 K
b1111111111111111111111111111111111111110101001111001110001101111 M
b1111111111111111111111111111111111111101101011000000110001001101 O
b0000000000000000000000000000000000000000000000001001001111101111 Q
b0000000000000000000000000000000000000000000000001001001111101111 S
#475000
0#
06
#480000
1#
1$
b11111101001010110000 %
b00001011101001001110 &
b11000100101101111101 '
b01000011101010010101 )
b01001001001110110110 *
b11100100101111010111 +
b11111111111110001010 -
b00000000000011010100 .
b11111111111101110101 /
b11010100010110101110 0
05
16
17
b11111101001010110000 8
b00001011101001001110 9
b11000100101101111101 :
b01000011101010010101 <
b01001001001110110110 =
b11100100101111010111 >
b11111111111110001010 @
b00000000000011010100 A
b11111111111101110101 B
b11010100010110101110 C
0H
#485000
0#
06
#490000
1#
0$
b00011101000111000011 1
b00100111100011010001 2
b11010011001110100101 3
15
16
07
b00011101000111000011 D
b00100111100011010001 E
b11010011001110100101 F
1H
b1111111111111111111111111111111111111111111101111101110010011001 I
b0000000000000000000000000000000000000000000100011111010110110100 K
b0000000000000000000000000000000000000000000010000010001101100111 M
b0000000000000000000000000000000000000000000100011111010110110100 O
b0000000000000000000000000000000000000000000000000111010000000000 Q
b0000000000000000000000000000000000000000000000000111010000000000 S
#495000
0#
06
