rtl/core/preprocessing/intersection.sv
module intersection #(
    parameter WIDTH = 16  // 12.4 format: 1 sign + 11 int + 4 frac = 16 bits
)(
    input  logic                    clk_i,
    input  logic                    start_i,
    
    // Line segment endpoints (v1 to v2)
    input  logic signed [WIDTH-1:0] v1_x,
    input  logic signed [WIDTH-1:0] v1_y,
    input  logic signed [WIDTH-1:0] v1_z,
    input  logic signed [WIDTH-1:0] v1_w,
    input  logic signed [WIDTH-1:0] v2_x,
    input  logic signed [WIDTH-1:0] v2_y,
    input  logic signed [WIDTH-1:0] v2_z,
    input  logic signed [WIDTH-1:0] v2_w,
    
    // Plane coefficients
    input  logic signed [WIDTH-1:0] plane_a,
    input  logic signed [WIDTH-1:0] plane_b,
    input  logic signed [WIDTH-1:0] plane_c,
    input  logic signed [WIDTH-1:0] plane_d,
    
    // Intersection point output
    output logic signed [WIDTH-1:0] intersect_x,
    output logic signed [WIDTH-1:0] intersect_y,
    output logic signed [WIDTH-1:0] intersect_z,
    output logic signed [WIDTH-1:0] intersect_w,
    
    output logic                    done_o
);

always_ff @(posedge clk_i) begin
    if (start_i) begin
        // Use 32 bits for intermediate calculations (16.16 format)
        logic signed [31:0] num;
        logic signed [31:0] den;
        logic signed [31:0] t;
        
        // Calculate numerator, scaling up by 16 bits
        // Note: When multiplying two 12.4 numbers, result is 24.8 format
        num = (-($signed(plane_a)*$signed(v1_x) + 
                 $signed(plane_b)*$signed(v1_y) + 
                 $signed(plane_c)*$signed(v1_z) + 
                 $signed(plane_d)*$signed(v1_w))) << 8; // Scale from 24.8 to 16.16
                 
        // Calculate denominator (24.8 format initially)
        den = ($signed(plane_a)*$signed(v2_x - v1_x) + 
               $signed(plane_b)*$signed(v2_y - v1_y) + 
               $signed(plane_c)*$signed(v2_z - v1_z) + 
               $signed(plane_d)*$signed(v2_w - v1_w));
               
        // Scale denominator to match numerator's 16.16 format
        den = den << 8;
        
        // Compute t while maintaining fixed-point precision (result in 16.16)
        t = (den == 0) ? 0 : (num / den);
        
        // Calculate intersections
        // When multiplying t (16.16) with v2-v1 (12.4), result needs to be shifted right by 16
        // to get back to 12.4 format
        intersect_x <= v1_x + ((t * $signed(v2_x - v1_x)) >>> 16);
        intersect_y <= v1_y + ((t * $signed(v2_y - v1_y)) >>> 16);
        intersect_z <= v1_z + ((t * $signed(v2_z - v1_z)) >>> 16);
        intersect_w <= v1_w + ((t * $signed(v2_w - v1_w)) >>> 16);

        done_o <= 1'b1;
    end else begin
        done_o <= 1'b0;
    end
end

endmodule

tb/test/core/preprocessing/dump.vcd
$version Generated by VerilatedVcd $end
$timescale 1ps $end
 $var wire 1 # clk_i $end
 $var wire 1 $ start_i $end
 $var wire 16 % v1_x [15:0] $end
 $var wire 16 & v1_y [15:0] $end
 $var wire 16 ' v1_z [15:0] $end
 $var wire 16 ( v1_w [15:0] $end
 $var wire 16 ) v2_x [15:0] $end
 $var wire 16 * v2_y [15:0] $end
 $var wire 16 + v2_z [15:0] $end
 $var wire 16 , v2_w [15:0] $end
 $var wire 16 - plane_a [15:0] $end
 $var wire 16 . plane_b [15:0] $end
 $var wire 16 / plane_c [15:0] $end
 $var wire 16 0 plane_d [15:0] $end
 $var wire 16 1 intersect_x [15:0] $end
 $var wire 16 2 intersect_y [15:0] $end
 $var wire 16 3 intersect_z [15:0] $end
 $var wire 16 4 intersect_w [15:0] $end
 $var wire 1 5 done_o $end
 $scope module intersection $end
  $var wire 32 L WIDTH [31:0] $end
  $var wire 1 6 clk_i $end
  $var wire 1 7 start_i $end
  $var wire 16 8 v1_x [15:0] $end
  $var wire 16 9 v1_y [15:0] $end
  $var wire 16 : v1_z [15:0] $end
  $var wire 16 ; v1_w [15:0] $end
  $var wire 16 < v2_x [15:0] $end
  $var wire 16 = v2_y [15:0] $end
  $var wire 16 > v2_z [15:0] $end
  $var wire 16 ? v2_w [15:0] $end
  $var wire 16 @ plane_a [15:0] $end
  $var wire 16 A plane_b [15:0] $end
  $var wire 16 B plane_c [15:0] $end
  $var wire 16 C plane_d [15:0] $end
  $var wire 16 D intersect_x [15:0] $end
  $var wire 16 E intersect_y [15:0] $end
  $var wire 16 F intersect_z [15:0] $end
  $var wire 16 G intersect_w [15:0] $end
  $var wire 1 H done_o $end
  $scope module unnamedblk1 $end
   $var wire 32 I num [31:0] $end
   $var wire 32 J den [31:0] $end
   $var wire 32 K t [31:0] $end
  $upscope $end
 $upscope $end
$enddefinitions $end


#0
1#
0$
b0000000000000000 %
b0000000000000000 &
b0000000000000000 '
b0000000000000000 (
b0000000000000000 )
b0000000000000000 *
b0000000000000000 +
b0000000000000000 ,
b0000000000000000 -
b0000000000000000 .
b0000000000000000 /
b0000000000000000 0
b0000000000000000 1
b0000000000000000 2
b0000000000000000 3
b0000000000000000 4
05
16
07
b0000000000000000 8
b0000000000000000 9
b0000000000000000 :
b0000000000000000 ;
b0000000000000000 <
b0000000000000000 =
b0000000000000000 >
b0000000000000000 ?
b0000000000000000 @
b0000000000000000 A
b0000000000000000 B
b0000000000000000 C
b0000000000000000 D
b0000000000000000 E
b0000000000000000 F
b0000000000000000 G
0H
b00000000000000000000000000000000 I
b00000000000000000000000000000000 J
b00000000000000000000000000000000 K
b00000000000000000000000000010000 L
#5000
0#
06
#10000
1#
16
#15000
0#
06
#20000
1#
16
#25000
0#
06
#30000
1#
16
#35000
0#
06
#40000
1#
1$
b0100010011111110 %
b1100010010100101 &
b1110010101001011 '
b0101010011010010 (
b1010011101010011 )
b0000011111010011 *
b1111000011010111 +
b0011010001001001 ,
b1100000100000100 -
b0011011111111100 .
b0001100000011001 /
b1111110010111111 0
16
17
b0100010011111110 8
b1100010010100101 9
b1110010101001011 :
b0101010011010010 ;
b1010011101010011 <
b0000011111010011 =
b1111000011010111 >
b0011010001001001 ?
b1100000100000100 @
b0011011111111100 A
b0001100000011001 B
b1111110010111111 C
#45000
0#
06
#50000
1#
0$
b0100010110110000 1
b1100010100011110 2
b1110010101011111 3
b0101010010010111 4
15
16
07
b0100010110110000 D
b1100010100011110 E
b1110010101011111 F
b0101010010010111 G
1H
b10001011111110111001101100000000 I
b11111111110000000001000100000000 J
b00000000000000000000000111010000 K
#55000
0#
06
#60000
1#
1$
b0100011001101000 %
b1010001011000101 &
b0010111011110011 '
b0000000110010001 (
b1100111011001110 )
b1101011011100111 *
b1100110010100011 +
b1111001011000001 ,
b0001001000101010 -
b1011010000110111 .
b0010010011000100 /
b0010000010010000 0
05
16
17
b0100011001101000 8
b1010001011000101 9
b0010111011110011 :
b0000000110010001 ;
b1100111011001110 <
b1101011011100111 =
b1100110010100011 >
b1111001011000001 ?
b0001001000101010 @
b1011010000110111 A
b0010010011000100 B
b0010000010010000 C
0H
#65000
0#
06
#70000
1#
0$
b0100011001100101 1
b1010001011000110 2
b0010111011110001 3
b0000000110010000 4
15
16
07
b0100011001100101 D
b1010001011000110 E
b0010111011110001 F
b0000000110010000 G
1H
b01110110100001110000000100000000 I
b00010011110011011100101000000000 J
b00000000000000000000000000000101 K
#75000
0#
06
#80000
1#
1$
b0100011011001000 %
b1111011011000110 &
b0011011000000011 '
b1110101010100000 (
b1011101011101101 )
b1010001100100111 *
b0100000011100001 +
b0101001011000001 ,
b0001110100000000 -
b1110011000011001 .
b1111011001100010 /
b1010110011001101 0
05
16
17
b0100011011001000 8
b1111011011000110 9
b0011011000000011 :
b1110101010100000 ;
b1011101011101101 <
b1010001100100111 =
b0100000011100001 >
b0101001011000001 ?
b0001110100000000 @
b1110011000011001 A
b1111011001100010 B
b1010110011001101 C
0H
#85000
0#
06
#90000
1#
0$
b0100011011001000 1
b1111011011000110 2
b0011011000000011 3
b1110101010100000 4
15
16
07
b0100011011001000 D
b1111011011000110 E
b0011011000000011 F
b1110101010100000 G
1H
b00100001011010010110010000000000 I
b01011110001101111110001000000000 J
b00000000000000000000000000000000 K
#95000
0#
06
#100000
1#
1$
b0100010111100100 %
b0000110000010001 &
b1100000110100100 '
b0001001000011111 (
b1100111111001111 )
b1100111100111000 *
b1100000011000000 +
b1101001011000101 ,
b1101111001110000 -
b1010111101010011 .
b1010001101100110 /
b1100000011000010 0
05
16
17
b0100010111100100 8
b0000110000010001 9
b1100000110100100 :
b0001001000011111 ;
b1100111111001111 <
b1100111100111000 =
b1100000011000000 >
b1101001011000101 ?
b1101111001110000 @
b1010111101010011 A
b1010001101100110 B
b1100000011000010 C
0H
#105000
0#
06
#110000
1#
0$
b0100010111100100 1
b0000110000010001 2
b1100000110100100 3
b0001001000011111 4
15
16
07
b0100010111100100 D
b0000110000010001 E
b1100000110100100 F
b0001001000011111 G
1H
b11100010100111001110011100000000 I
b10100001000001100110100100000000 J
#115000
0#
06
#120000
1#
1$
b1100000001011101 %
b1101101001111001 &
b0100111001110110 '
b1011110010101011 (
b0010010010011100 )
b0011100110100101 *
b0101100001100011 +
b1011101111000011 ,
b1110000010101001 -
b1110011011110110 .
b0001111110001111 /
b1010110100001001 0
05
16
17
b1100000001011101 8
b1101101001111001 9
b0100111001110110 :
b1011110010101011 ;
b0010010010011100 <
b0011100110100101 =
b0101100001100011 >
b1011101111000011 ?
b1110000010101001 @
b1110011011110110 A
b0001111110001111 B
b1010110100001001 C
0H
#125000
0#
06
#130000
1#
0$
b1100000001011101 1
b1101101001111001 2
b0100111001110110 3
b1011110010101011 4
15
16
07
b1100000001011101 D
b1101101001111001 E
b0100111001110110 F
b1011110010101011 G
1H
b00001011101011010110100000000000 I
b11101111101110000001101000000000 J
#135000
0#
06
#140000
1#
1$
b1010010000100000 %
b0101010100001110 &
b0001110100010000 '
b0001110100100110 (
b1101111101100100 )
b1011111111011010 *
b0011001100001101 +
b0100001011010011 ,
b0001100101010101 -
b1011011100001011 .
b1011011110011000 /
b1100111110111101 0
05
16
17
b1010010000100000 8
b0101010100001110 9
b0001110100010000 :
b0001110100100110 ;
b1101111101100100 <
b1011111111011010 =
b0011001100001101 >
b0100001011010011 ?
b0001100101010101 @
b1011011100001011 A
b1011011110011000 B
b1100111110111101 C
0H
#145000
0#
06
#150000
1#
0$
b1010010000100000 1
b0101010100001110 2
b0001110100010000 3
b0001110100100110 4
15
16
07
b1010010000100000 D
b0101010100001110 E
b0001110100010000 F
b0001110100100110 G
1H
b00001011110001110011100000000000 I
b00011011010110010100100100000000 J
#155000
0#
06
#160000
1#
1$
b0010010100101001 %
b0011000000000011 &
b1111011111101110 '
b0010110001111101 (
b0000000101000010 )
b0101000100010100 *
b1011010001111001 +
b0011011100110000 ,
b0011000101101101 -
b0011011100011110 .
b0011111110011001 /
b1100111110001110 0
05
16
17
b0010010100101001 8
b0011000000000011 9
b1111011111101110 :
b0010110001111101 ;
b0000000101000010 <
b0101000100010100 =
b1011010001111001 >
b0011011100110000 ?
b0011000101101101 @
b0011011100011110 A
b0011111110011001 B
b1100111110001110 C
0H
#165000
0#
06
#170000
1#
0$
b0010010100101001 1
b0011000000000011 2
b1111011111101110 3
b0010110001111101 4
15
16
07
b0010010100101001 D
b0011000000000011 E
b1111011111101110 F
b0010110001111101 G
1H
b11101001100011111001110100000000 I
b01100111100101110000000000000000 J
#175000
0#
06
#180000
1#
1$
b1111011101101101 %
b0000011101001110 &
b1110000000110111 '
b1110001111101110 (
b1111011001100010 )
b1010110111000011 *
b1100001010100011 +
b0000110000100011 ,
b1110011111110110 -
b1110100100111101 .
b0101010101111100 /
b0100101010100010 0
05
16
17
b1111011101101101 8
b0000011101001110 9
b1110000000110111 :
b1110001111101110 ;
b1111011001100010 <
b1010110111000011 =
b1100001010100011 >
b0000110000100011 ?
b1110011111110110 @
b1110100100111101 A
b0101010101111100 B
b0100101010100010 C
0H
#185000
0#
06
#190000
1#
0$
b1111011101101100 1
b0000011101001100 2
b1110000000110110 3
b1110001111101110 4
15
16
07
b1111011101101100 D
b0000011101001100 E
b1110000000110110 F
b1110001111101110 G
1H
b10100100010000000110110000000000 I
b11100111100001010010100100000000 J
b00000000000000000000000000000011 K
#195000
0#
06
#200000
1#
1$
b0000010010011011 %
b0101000111010111 &
b0001011000010011 '
b0010000000011010 (
b1010110110010111 )
b0011110110111111 *
b0011000001101101 +
b1110011100101100 ,
b0001110110101001 -
b0011101010011000 .
b1101110000110101 /
b0011100111001100 0
05
16
17
b0000010010011011 8
b0101000111010111 9
b0001011000010011 :
b0010000000011010 ;
b1010110110010111 <
b0011110110111111 =
b0011000001101101 >
b1110011100101100 ?
b0001110110101001 @
b0011101010011000 A
b1101110000110101 B
b0011100111001100 C
0H
#205000
0#
06
#210000
1#
0$
b0000010010011010 1
b0101000111010110 2
b0001011000010011 3
b0010000000011001 4
15
16
07
b0000010010011010 D
b0101000111010110 E
b0001011000010011 F
b0010000000011001 G
1H
b10010010110101000101111000000000 I
b11001000001011010001011000000000 J
b00000000000000000000000000000001 K
#215000
0#
06
#220000
1#
1$
b1101110100001110 %
b1011111110011100 &
b0100000010111000 '
b1011110110100111 (
b1111010101001100 )
b0100111011101001 *
b1101101000011110 +
b0000110110111100 ,
b0101000010111100 -
b1110100000001101 .
b1100011110110110 /
b1110110000111100 0
05
16
17
b1101110100001110 8
b1011111110011100 9
b0100000010111000 :
b1011110110100111 ;
b1111010101001100 <
b0100111011101001 =
b1101101000011110 >
b0000110110111100 ?
b0101000010111100 @
b1110100000001101 A
b1100011110110110 B
b1110110000111100 C
0H
#225000
0#
06
#230000
1#
0$
b1101110100001110 1
b1011111110011100 2
b0100000010111000 3
b1011110110100111 4
15
16
07
b1101110100001110 D
b1011111110011100 E
b0100000010111000 F
b1011110110100111 G
1H
b00011010101111001101100000000000 I
b10010000101101011110000100000000 J
b00000000000000000000000000000000 K
#235000
0#
06
#240000
1#
1$
b0100010100111010 %
b1010001101000001 &
b0101001000110111 '
b0101100111111000 (
b0100000100001110 )
b0010100001100010 *
b0100111111110100 +
b1110100111100111 ,
b0100011001110101 -
b0001100111011111 .
b0011010111110111 /
b0100011011111100 0
05
16
17
b0100010100111010 8
b1010001101000001 9
b0101001000110111 :
b0101100111111000 ;
b0100000100001110 <
b0010100001100010 =
b0100111111110100 >
b1110100111100111 ?
b0100011001110101 @
b0001100111011111 A
b0011010111110111 B
b0100011011111100 C
0H
#245000
0#
06
#250000
1#
0$
b0100010100111010 1
b1010001101000001 2
b0101001000110111 3
b0101100111111000 4
15
16
07
b0100010100111010 D
b1010001101000001 E
b0101001000110111 F
b0101100111111000 G
1H
b00001010110110111010111000000000 I
b11100010001111000100001000000000 J
#255000
0#
06
#260000
1#
1$
b0011110101011101 %
b0100001110101110 &
b1011001000111010 '
b1101101001001001 (
b0001000010111111 )
b1101011011011011 *
b0001111100100100 +
b0010110001011110 ,
b1110110101000000 -
b1100000100000110 .
b0101011100011101 /
b0101101001101011 0
05
16
17
b0011110101011101 8
b0100001110101110 9
b1011001000111010 :
b1101101001001001 ;
b0001000010111111 <
b1101011011011011 =
b0001111100100100 >
b0010110001011110 ?
b1110110101000000 @
b1100000100000110 A
b0101011100011101 B
b0101101001101011 C
0H
#265000
0#
06
#270000
1#
0$
b0011110101011101 1
b0100001110101110 2
b1011001000111010 3
b1101101001001001 4
15
16
07
b0011110101011101 D
b0100001110101110 E
b1011001000111010 F
b1101101001001001 G
1H
b11101101111111101001011100000000 I
b00010111011111111101011100000000 J
#275000
0#
06
#280000
1#
1$
b0101000010110001 %
b1111001110010000 &
b1100111100100110 '
b0010010111110110 (
b0010100101010011 )
b1010101001110110 *
b0010111101010001 +
b1011111100110011 ,
b0010010110111100 -
b1011111101100010 .
b1110001100101001 /
b1011001101101110 0
05
16
17
b0101000010110001 8
b1111001110010000 9
b1100111100100110 :
b0010010111110110 ;
b0010100101010011 <
b1010101001110110 =
b0010111101010001 >
b1011111100110011 ?
b0010010110111100 @
b1011111101100010 A
b1110001100101001 B
b1011001101101110 C
0H
#285000
0#
06
#290000
1#
0$
b0101000010110001 1
b1111001110010000 2
b1100111100100110 3
b0010010111110110 4
15
16
07
b0101000010110001 D
b1111001110010000 E
b1100111100100110 F
b0010010111110110 G
1H
b11010001010010110001101000000000 I
b10001101001001100001110100000000 J
#295000
0#
06
#300000
1#
1$
b0000011111100000 %
b0011010000011011 &
b0011000000011000 '
b1100000010001100 (
b0010010001000010 )
b0100111000001010 *
b0011001111101100 +
b0101010000110101 ,
b0001000001111010 -
b1010011110001011 .
b1111111111110100 /
b0011010000001111 0
05
16
17
b0000011111100000 8
b0011010000011011 9
b0011000000011000 :
b1100000010001100 ;
b0010010001000010 <
b0100111000001010 =
b0011001111101100 >
b0101010000110101 ?
b0001000001111010 @
b1010011110001011 A
b1111111111110100 B
b0011010000001111 C
0H
#305000
0#
06
#310000
1#
0$
b0000011111011111 1
b0011010000011010 2
b0011000000010111 3
b1100000010001100 4
15
16
07
b0000011111011111 D
b0011010000011010 E
b0011000000010111 F
b1100000010001100 G
1H
b01101000111000001000001100000000 I
b11010101011100010111000000000000 J
b11111111111111111111111111111110 K
#315000
0#
06
#320000
1#
1$
b0101100100010100 %
b1101011100010111 &
b1010010010100001 '
b1101101110011110 (
b1111010111101100 )
b0011110000101011 *
b0000001011100010 +
b0101000011011000 ,
b0010111001011011 -
b1111000100000110 .
b0000100010101010 /
b1111111101111001 0
05
16
17
b0101100100010100 8
b1101011100010111 9
b1010010010100001 :
b1101101110011110 ;
b1111010111101100 <
b0011110000101011 =
b0000001011100010 >
b0101000011011000 ?
b0010111001011011 @
b1111000100000110 A
b0000100010101010 B
b1111111101111001 C
0H
#325000
0#
06
#330000
1#
0$
b0101100100010001 1
b1101011100011001 2
b1010010010100011 3
b1101101110100000 4
15
16
07
b0101100100010001 D
b1101011100011001 E
b1010010010100011 F
b1101101110100000 G
1H
b01111110100000011100001000000000 I
b00010100100100001101010000000000 J
b00000000000000000000000000000110 K
#335000
0#
06
#340000
1#
1$
b0011001000001110 %
b1101010011110110 &
b1101111001001100 '
b0001000010000111 (
b0010010111101011 )
b0100100010101110 *
b0011100110000001 +
b0100110110100000 ,
b1011010010101011 -
b0011111000011100 .
b1111111111010000 /
b0100110001001011 0
05
16
17
b0011001000001110 8
b1101010011110110 9
b1101111001001100 :
b0001000010000111 ;
b0010010111101011 <
b0100100010101110 =
b0011100110000001 >
b0100110110100000 ?
b1011010010101011 @
b0011111000011100 A
b1111111111010000 B
b0100110001001011 C
0H
#345000
0#
06
#350000
1#
0$
b0011001000001110 1
b1101010011110101 2
b1101111001001011 3
b0001000010000110 4
15
16
07
b0011001000001110 D
b1101010011110101 E
b1101111001001011 F
b0001000010000110 G
1H
b00111000100111000111000100000000 I
b11001001101110010010001000000000 J
b11111111111111111111111111111111 K
#355000
0#
06
#360000
1#
1$
b1100111010010111 %
b0001001100011010 &
b0101010111100110 '
b0000001000011110 (
b0001000001110010 )
b1101000101011111 *
b0000011101001001 +
b1100001101100010 ,
b1111100011001101 -
b0000000110000001 .
b1111010100001111 /
b0000100000010100 0
05
16
17
b1100111010010111 8
b0001001100011010 9
b0101010111100110 :
b0000001000011110 ;
b0001000001110010 <
b1101000101011111 =
b0000011101001001 >
b1100001101100010 ?
b1111100011001101 @
b0000000110000001 A
b1111010100001111 B
b0000100000010100 C
0H
#365000
0#
06
#370000
1#
0$
b1100111010010111 1
b0001001100011010 2
b0101010111100110 3
b0000001000011110 4
15
16
07
b1100111010010111 D
b0001001100011010 E
b0101010111100110 F
b0000001000011110 G
1H
b00011010010011100010100100000000 I
b00100100011001110100000100000000 J
b00000000000000000000000000000000 K
#375000
0#
06
#380000
1#
1$
b1111100001111111 %
b1011011011001011 &
b0001000011001000 '
b0011010110001011 (
b0101000111111001 )
b0010111000010111 *
b0100001011110101 +
b0011010001100100 ,
b0001101010101011 -
b1011101000010000 .
b1011000001101111 /
b0100110111111001 0
05
16
17
b1111100001111111 8
b1011011011001011 9
b0001000011001000 :
b0011010110001011 ;
b0101000111111001 <
b0010111000010111 =
b0100001011110101 >
b0011010001100100 ?
b0001101010101011 @
b1011101000010000 A
b1011000001101111 B
b0100110111111001 C
0H
#385000
0#
06
#390000
1#
0$
b1111100001111111 1
b1011011011001011 2
b0001000011001000 3
b0011010110001010 4
15
16
07
b1111100001111111 D
b1011011011001011 E
b0001000011001000 F
b0011010110001010 G
1H
b10110000100010001001000000000000 I
b11001000101011001101001000000000 J
b00000000000000000000000000000001 K
#395000
0#
06
#400000
1#
1$
b0100111000000100 %
b0101100100010100 &
b0101000011001110 '
b0101011100111100 (
b0001001011101101 )
b1110111010111100 *
b0101000001001001 +
b0010010101101101 ,
b1100110011000110 -
b1111010011100000 .
b0100010111110111 /
b0000000000101110 0
05
16
17
b0100111000000100 8
b0101100100010100 9
b0101000011001110 :
b0101011100111100 ;
b0001001011101101 <
b1110111010111100 =
b0101000001001001 >
b0010010101101101 ?
b1100110011000110 @
b1111010011100000 A
b0100010111110111 B
b0000000000101110 C
0H
#405000
0#
06
#410000
1#
0$
b0100111000000011 1
b0101100100010011 2
b0101000011001101 3
b0101011100111011 4
15
16
07
b0100111000000011 D
b0101100100010011 E
b0101000011001101 F
b0101011100111011 G
1H
b01010110010011011101111000000000 I
b01000100101111101011000100000000 J
#415000
0#
06
#420000
1#
1$
b0100100111011001 %
b1111110100101010 &
b0100111001010101 '
b1101011100111101 (
b0010010100100111 )
b0001101011001111 *
b1011001111011110 +
b0011110110000001 ,
b0000010101001010 -
b1111101010110001 .
b0000000000101001 /
b0001011001111110 0
05
16
17
b0100100111011001 8
b1111110100101010 9
b0100111001010101 :
b1101011100111101 ;
b0010010100100111 <
b0001101011001111 =
b1011001111011110 >
b0011110110000001 ?
b0000010101001010 @
b1111101010110001 A
b0000000000101001 B
b0001011001111110 C
0H
#425000
0#
06
#430000
1#
0$
b0100100111011001 1
b1111110100101010 2
b0100111001010101 3
b1101011100111101 4
15
16
07
b0100100111011001 D
b1111110100101010 E
b0100111001010101 F
b1101011100111101 G
1H
b11110010101000101001100100000000 I
b10101100111111000000101000000000 J
b00000000000000000000000000000000 K
#435000
0#
06
#440000
1#
1$
b1011100001100111 %
b1010011100110101 &
b1101011101000000 '
b0100000000001101 (
b0000111111000110 )
b0010010101100101 *
b0001101111110100 +
b1110110001010001 ,
b0001101010101000 -
b0001101101001010 .
b1101001000011101 /
b1101111000101000 0
05
16
17
b1011100001100111 8
b1010011100110101 9
b1101011101000000 :
b0100000000001101 ;
b0000111111000110 <
b0010010101100101 =
b0001101111110100 >
b1110110001010001 ?
b0001101010101000 @
b0001101101001010 A
b1101001000011101 B
b1101111000101000 C
0H
#445000
0#
06
#450000
1#
0$
b1011100001100111 1
b1010011100110101 2
b1101011101000000 3
b0100000000001101 4
15
16
07
b1011100001100111 D
b1010011100110101 E
b1101011101000000 F
b0100000000001101 G
1H
b00010101011011111100111000000000 I
b01001101110110010011110000000000 J
#455000
0#
06
#460000
1#
1$
b1100000001100110 %
b1111010011001010 &
b0100110111111111 '
b0000110111011001 (
b0001011111100010 )
b1110111000110111 *
b1010111001011111 +
b1010101001101111 ,
b1011001100000110 -
b1100100001100110 .
b0100101110101011 /
b1010110101100011 0
05
16
17
b1100000001100110 8
b1111010011001010 9
b0100110111111111 :
b0000110111011001 ;
b0001011111100010 <
b1110111000110111 =
b1010111001011111 >
b1010101001101111 ?
b1011001100000110 @
b1100100001100110 A
b0100101110101011 B
b1010110101100011 C
0H
#465000
0#
06
#470000
1#
0$
b1100000001100110 1
b1111010011001010 2
b0100110111111111 3
b0000110111011001 4
15
16
07
b1100000001100110 D
b1111010011001010 E
b0100110111111111 F
b0000110111011001 G
1H
b11011011000001001110000000000000 I
b10110000101101100111100000000000 J
#475000
0#
06
#480000
1#
1$
b0100001011010011 %
b1101100110110011 &
b0101001000110000 '
b1100110100101010 (
b0000101110000001 )
b1111001001000011 *
b0000101101100011 +
b1010001011010111 ,
b0101010010011010 -
b1110110000111101 .
b0010001111011010 /
b1010011001011110 0
05
16
17
b0100001011010011 8
b1101100110110011 9
b0101001000110000 :
b1100110100101010 ;
b0000101110000001 <
b1111001001000011 =
b0000101101100011 >
b1010001011010111 ?
b0101010010011010 @
b1110110000111101 A
b0010001111011010 B
b1010011001011110 C
0H
#485000
0#
06
#490000
1#
0$
b0100001011010010 1
b1101100110110011 2
b0101001000101111 3
b1100110100101001 4
15
16
07
b0100001011010010 D
b1101100110110011 E
b0101001000101111 F
b1100110100101001 G
1H
b10100110100011110001111100000000 I
b10111001101111001111000000000000 J
b00000000000000000000000000000001 K
#495000
0#
06
#500000
1#
1$
b0010001110101010 %
b0011001110100101 &
b0100011101110011 '
b1111100000111001 (
b0101101111110011 )
b0010010000001110 *
b0000001111111101 +
b1100000011010011 ,
b0011110101111101 -
b1110100010000110 .
b1101010001111011 /
b0010111010000101 0
05
16
17
b0010001110101010 8
b0011001110100101 9
b0100011101110011 :
b1111100000111001 ;
b0101101111110011 <
b0010010000001110 =
b0000001111111101 >
b1100000011010011 ?
b0011110101111101 @
b1110100010000110 A
b1101010001111011 B
b0010111010000101 C
0H
#505000
0#
06
#510000
1#
0$
b0010001110101010 1
b0011001110100101 2
b0100011101110011 3
b1111100000111001 4
15
16
07
b0010001110101010 D
b0011001110100101 E
b0100011101110011 F
b1111100000111001 G
1H
b10111010101111111100001000000000 I
b01011001101000011110101100000000 J
b00000000000000000000000000000000 K
#515000
0#
06
#520000
1#
1$
b1111000110100100 %
b0001110101011001 &
b0011010010011110 '
b1110010010001010 (
b1011000010000011 )
b1110101100000010 *
b1011100000111110 +
b1111100000000111 ,
b1101001011100111 -
b1101110010001111 .
b1110011011100000 /
b1110111010010001 0
05
16
17
b1111000110100100 8
b0001110101011001 9
b0011010010011110 :
b1110010010001010 ;
b1011000010000011 <
b1110101100000010 =
b1011100000111110 >
b1111100000000111 ?
b1101001011100111 @
b1101110010001111 A
b1110011011100000 B
b1110111010010001 C
0H
#525000
0#
06
#530000
1#
0$
b1111000110100100 1
b0001110101011001 2
b0011010010011110 3
b1110010010001010 4
15
16
07
b1111000110100100 D
b0001110101011001 E
b0011010010011110 F
b1110010010001010 G
1H
b11010011110011111110001100000000 I
b01010010011100100110110100000000 J
#535000
0#
06
#540000
1#
1$
b0000101001101011 %
b1010110000001001 &
b1110100001100010 '
b1010010101011100 (
b0011100110100101 )
b1111111011011100 *
b1101001101011100 +
b1111000110000000 ,
b0100000010111001 -
b1100101101101000 .
b0101000001100001 /
b1101010101101010 0
05
16
17
b0000101001101011 8
b1010110000001001 9
b1110100001100010 :
b1010010101011100 ;
b0011100110100101 <
b1111111011011100 =
b1101001101011100 >
b1111000110000000 ?
b0100000010111001 @
b1100101101101000 A
b0101000001100001 B
b1101010101101010 C
0H
#545000
0#
06
#550000
1#
0$
b0000101001101010 1
b1010110000001000 2
b1110100001100010 3
b1010010101011011 4
15
16
07
b0000101001101010 D
b1010110000001000 E
b1110100001100010 F
b1010010101011011 G
1H
b01110100000000001100101100000000 I
b10101000001110110100010000000000 J
b11111111111111111111111111111111 K
#555000
0#
06
#560000
1#
1$
b0011101110001111 %
b0000000111101111 &
b0010101110101011 '
b1110001000110001 (
b0000001010111000 )
b0001101010010100 *
b1110011111000101 +
b1011110010111101 ,
b1011101100010001 -
b0100111100110010 .
b1110111101000001 /
b0100101011111001 0
05
16
17
b0011101110001111 8
b0000000111101111 9
b0010101110101011 :
b1110001000110001 ;
b0000001010111000 <
b0001101010010100 =
b1110011111000101 >
b1011110010111101 ?
b1011101100010001 @
b0100111100110010 A
b1110111101000001 B
b0100101011111001 C
0H
#565000
0#
06
#570000
1#
0$
b0011101110001111 1
b0000000111101111 2
b0010101110101011 3
b1110001000110001 4
15
16
07
b0011101110001111 D
b0000000111101111 E
b0010101110101011 F
b1110001000110001 G
1H
b00000110100011011011111100000000 I
b01100110111110101011100100000000 J
b00000000000000000000000000000000 K
#575000
0#
06
#580000
1#
1$
b0001010001101010 %
b0101011011110100 &
b0101100011010100 '
b0011001101101100 (
b0101101110101001 )
b1101101100110010 *
b0101000101100000 +
b1011100011110111 ,
b1100111100101110 -
b0100001100100010 .
b0100000111110100 /
b0100010110110010 0
05
16
17
b0001010001101010 8
b0101011011110100 9
b0101100011010100 :
b0011001101101100 ;
b0101101110101001 <
b1101101100110010 =
b0101000101100000 >
b1011100011110111 ?
b1100111100101110 @
b0100001100100010 A
b0100000111110100 B
b0100010110110010 C
0H
#585000
0#
06
#590000
1#
0$
b0001010001101010 1
b0101011011110100 2
b0101100011010100 3
b0011001101101100 4
15
16
07
b0001010001101010 D
b0101011011110100 E
b0101100011010100 F
b0011001101101100 G
1H
b00110100110110110110010000000000 I
b10110011010010111010010000000000 J
#595000
0#
06
#600000
1#
1$
b0001000000011000 %
b0000101011110111 &
b0000101000110110 '
b1010101111011000 (
b1100110010111101 )
b0000100100001100 *
b0001011000010001 +
b1111010101001110 ,
b0010011001001010 -
b1011111011111000 .
b0101101000010101 /
b1111111000111111 0
05
16
17
b0001000000011000 8
b0000101011110111 9
b0000101000110110 :
b1010101111011000 ;
b1100110010111101 <
b0000100100001100 =
b0001011000010001 >
b1111010101001110 ?
b0010011001001010 @
b1011111011111000 A
b0101101000010101 B
b1111111000111111 C
0H
#605000
0#
06
#610000
1#
0$
b0001000000010111 1
b0000101011110110 2
b0000101000110110 3
b1010101111011000 4
15
16
07
b0001000000010111 D
b0000101011110110 E
b0000101000110110 F
b1010101111011000 G
1H
b00110101011010110011001000000000 I
b00010100110111110000101100000000 J
b00000000000000000000000000000010 K
#615000
0#
06
