rtl/core/preprocessing/intersection.sv
module intersection #(
    // 1 sign + 11 int + 12 frac = 24 bits total
    parameter WIDTH = 24  
)(
    input  logic                    clk_i,
    input  logic                    start_i,
    
    // Line segment endpoints (v1 to v2), each in 12.12 fixed point
    input  logic signed [WIDTH-1:0] v1_x,
    input  logic signed [WIDTH-1:0] v1_y,
    input  logic signed [WIDTH-1:0] v1_z,
    input  logic signed [WIDTH-1:0] v1_w,
    input  logic signed [WIDTH-1:0] v2_x,
    input  logic signed [WIDTH-1:0] v2_y,
    input  logic signed [WIDTH-1:0] v2_z,
    input  logic signed [WIDTH-1:0] v2_w,
    
    // Plane coefficients (a,b,c,d), each in 12.12 fixed point
    input  logic signed [WIDTH-1:0] plane_a,
    input  logic signed [WIDTH-1:0] plane_b,
    input  logic signed [WIDTH-1:0] plane_c,
    input  logic signed [WIDTH-1:0] plane_d,
    
    // Intersection point output in 12.12 fixed point (on segment)
    output logic signed [WIDTH-1:0] intersect_x,
    output logic signed [WIDTH-1:0] intersect_y,
    output logic signed [WIDTH-1:0] intersect_z,
    output logic signed [WIDTH-1:0] intersect_w,
    
    output logic                    done_o
);

always_ff @(posedge clk_i) begin
    if (start_i) begin
        // 64-bit accumulators to avoid overflow
        logic signed [63:0] sum_v1, sum_diff;
        logic signed [63:0] num, den;
        logic signed [63:0] t_raw;      // t in Q12, before clamping
        logic signed [63:0] t_clamped;  // t in Q12, clamped to [0,1]

        // For reference: 1.0 in Q12 is 4096
        localparam logic signed [63:0] Q12_ZERO = 64'd0;
        localparam logic signed [63:0] Q12_ONE  = 64'd4096;  // (1 << 12)

        //==================================================
        // plane . v1  => (plane_a * v1_x + plane_b * v1_y + ...)
        // Each multiply is (12 frac + 12 frac) => 24 frac bits.
        // sum_v1 is thus effectively Q24 in 64-bit container.
        //==================================================
        sum_v1 = (plane_a * v1_x)
               + (plane_b * v1_y)
               + (plane_c * v1_z)
               + (plane_d * v1_w);

        // num = -(plane . v1)  => still Q24
        num = -sum_v1;

        //==================================================
        // plane . (v2 - v1)
        //==================================================
        sum_diff = (plane_a * (v2_x - v1_x))
                 + (plane_b * (v2_y - v1_y))
                 + (plane_c * (v2_z - v1_z))
                 + (plane_d * (v2_w - v1_w));
        den = sum_diff;  // Q24

        //==================================================
        // Compute t in Q12:
        //   t = (num << 12) / den
        // 
        // Here: num, den are Q24. So:
        //   (num << 12) => Q24 shifted left by 12 => Q36
        //   Q36 / Q24 => Q12 result
        //==================================================
        if (den == 0) begin
            // Degenerate: line parallel to plane => no intersection or infinite
            t_raw = 0;  
        end
        else begin
            t_raw = (num <<< 12) / den;  
        end

        // Clamp t to [0, 1] in Q12
        if (t_raw < Q12_ZERO) begin
            t_clamped = Q12_ZERO;  // intersection effectively at v1
        end
        else if (t_raw > Q12_ONE) begin
            t_clamped = Q12_ONE;   // intersection effectively at v2
        end
        else begin
            t_clamped = t_raw;
        end

        //========================================================
        // Intersection in 12.12 (clamped to segment):
        //   intersect = v1 + [t_clamped * (v2 - v1) >> 12]
        //
        // (v2 - v1) is Q12, t_clamped is Q12 => product Q24,
        // shift right by 12 => back to Q12
        //========================================================
        intersect_x <= v1_x + ((t_clamped * (v2_x - v1_x)) >>> 12);
        intersect_y <= v1_y + ((t_clamped * (v2_y - v1_y)) >>> 12);
        intersect_z <= v1_z + ((t_clamped * (v2_z - v1_z)) >>> 12);
        intersect_w <= v1_w + ((t_clamped * (v2_w - v1_w)) >>> 12);

        done_o <= 1'b1;
    end
    else begin
        done_o <= 1'b0;
    end
end

endmodule

tb/test/core/preprocessing/dump.vcd
$version Generated by VerilatedVcd $end
$timescale 1ps $end
 $var wire 1 # clk_i $end
 $var wire 1 $ start_i $end
 $var wire 24 % v1_x [23:0] $end
 $var wire 24 & v1_y [23:0] $end
 $var wire 24 ' v1_z [23:0] $end
 $var wire 24 ( v1_w [23:0] $end
 $var wire 24 ) v2_x [23:0] $end
 $var wire 24 * v2_y [23:0] $end
 $var wire 24 + v2_z [23:0] $end
 $var wire 24 , v2_w [23:0] $end
 $var wire 24 - plane_a [23:0] $end
 $var wire 24 . plane_b [23:0] $end
 $var wire 24 / plane_c [23:0] $end
 $var wire 24 0 plane_d [23:0] $end
 $var wire 24 1 intersect_x [23:0] $end
 $var wire 24 2 intersect_y [23:0] $end
 $var wire 24 3 intersect_z [23:0] $end
 $var wire 24 4 intersect_w [23:0] $end
 $var wire 1 5 done_o $end
 $scope module intersection $end
  $var wire 32 U WIDTH [31:0] $end
  $var wire 1 6 clk_i $end
  $var wire 1 7 start_i $end
  $var wire 24 8 v1_x [23:0] $end
  $var wire 24 9 v1_y [23:0] $end
  $var wire 24 : v1_z [23:0] $end
  $var wire 24 ; v1_w [23:0] $end
  $var wire 24 < v2_x [23:0] $end
  $var wire 24 = v2_y [23:0] $end
  $var wire 24 > v2_z [23:0] $end
  $var wire 24 ? v2_w [23:0] $end
  $var wire 24 @ plane_a [23:0] $end
  $var wire 24 A plane_b [23:0] $end
  $var wire 24 B plane_c [23:0] $end
  $var wire 24 C plane_d [23:0] $end
  $var wire 24 D intersect_x [23:0] $end
  $var wire 24 E intersect_y [23:0] $end
  $var wire 24 F intersect_z [23:0] $end
  $var wire 24 G intersect_w [23:0] $end
  $var wire 1 H done_o $end
  $scope module unnamedblk1 $end
   $var wire 64 I sum_v1 [63:0] $end
   $var wire 64 K sum_diff [63:0] $end
   $var wire 64 M num [63:0] $end
   $var wire 64 O den [63:0] $end
   $var wire 64 Q t_raw [63:0] $end
   $var wire 64 S t_clamped [63:0] $end
   $var wire 64 V Q12_ZERO [63:0] $end
   $var wire 64 X Q12_ONE [63:0] $end
  $upscope $end
 $upscope $end
$enddefinitions $end


#0
1#
0$
b000000000000000000000000 %
b000000000000000000000000 &
b000000000000000000000000 '
b000000000000000000000000 (
b000000000000000000000000 )
b000000000000000000000000 *
b000000000000000000000000 +
b000000000000000000000000 ,
b000000000000000000000000 -
b000000000000000000000000 .
b000000000000000000000000 /
b000000000000000000000000 0
b000000000000000000000000 1
b000000000000000000000000 2
b000000000000000000000000 3
b000000000000000000000000 4
05
16
07
b000000000000000000000000 8
b000000000000000000000000 9
b000000000000000000000000 :
b000000000000000000000000 ;
b000000000000000000000000 <
b000000000000000000000000 =
b000000000000000000000000 >
b000000000000000000000000 ?
b000000000000000000000000 @
b000000000000000000000000 A
b000000000000000000000000 B
b000000000000000000000000 C
b000000000000000000000000 D
b000000000000000000000000 E
b000000000000000000000000 F
b000000000000000000000000 G
0H
b0000000000000000000000000000000000000000000000000000000000000000 I
b0000000000000000000000000000000000000000000000000000000000000000 K
b0000000000000000000000000000000000000000000000000000000000000000 M
b0000000000000000000000000000000000000000000000000000000000000000 O
b0000000000000000000000000000000000000000000000000000000000000000 Q
b0000000000000000000000000000000000000000000000000000000000000000 S
b00000000000000000000000000011000 U
b0000000000000000000000000000000000000000000000000000000000000000 V
b0000000000000000000000000000000000000000000000000001000000000000 X
#5000
0#
06
#10000
1#
16
#15000
0#
06
#20000
1#
16
#25000
0#
06
#30000
1#
16
#35000
0#
06
#40000
1#
1$
b010000110101101010110111 %
b000101110010011100001111 &
b110010001100110010101110 '
b000000000001000000000000 (
b000110011100101000010010 )
b010011110101000110000010 *
b110100010101011010000101 +
b000000000001000000000000 ,
b111111111111110001101100 -
b000000000000011111001001 .
b000000000000000001110000 /
b111001100010000111001111 0
16
17
b010000110101101010110111 8
b000101110010011100001111 9
b110010001100110010101110 :
b000000000001000000000000 ;
b000110011100101000010010 <
b010011110101000110000010 =
b110100010101011010000101 >
b000000000001000000000000 ?
b111111111111110001101100 @
b000000000000011111001001 A
b000000000000000001110000 B
b111001100010000111001111 C
#45000
0#
06
#50000
1#
0$
b001000000011001111100011 1
b010001101010011011110101 2
b110100000000010101000000 3
b000000000001000000000000 4
15
16
07
b001000000011001111100011 D
b010001101010011011110101 E
b110100000000010101000000 F
b000000000001000000000000 G
1H
b1111111111111111111111111111111000001101001101001111100100011011 I
b0000000000000000000000000000001001001101101110000101010110111111 K
b0000000000000000000000000000000111110010110010110000011011100101 M
b0000000000000000000000000000001001001101101110000101010110111111 O
b0000000000000000000000000000000000000000000000000000110110001000 Q
b0000000000000000000000000000000000000000000000000000110110001000 S
#55000
0#
06
#60000
1#
1$
b000101000011000110011100 %
b101100110011110100110111 &
b000000000111010011101111 '
b000111100010001101011101 )
b111101100010100111000100 *
b001000110001111101110001 +
b111111111111001000111111 -
b111111111111011111101001 .
b000000000000000001000111 /
b000011110001100101001011 0
05
16
17
b000101000011000110011100 8
b101100110011110100110111 9
b000000000111010011101111 :
b000111100010001101011101 <
b111101100010100111000100 =
b001000110001111101110001 >
b111111111111001000111111 @
b111111111111011111101001 A
b000000000000000001000111 B
b000011110001100101001011 C
0H
#65000
0#
06
#70000
1#
0$
b000111001110010010000101 1
b111011011100100000000011 2
b000111101100011111110110 3
15
16
07
b000111001110010010000101 D
b111011011100100000000011 E
b000111101100011111110110 F
1H
b0000000000000000000000000000001001001000111100101001001110111100 I
b1111111111111111111111111111110101100011011011111001000111100010 K
b1111111111111111111111111111110110110111000011010110110001000100 M
b1111111111111111111111111111110101100011011011111001000111100010 O
b0000000000000000000000000000000000000000000000000000110111111111 Q
b0000000000000000000000000000000000000000000000000000110111111111 S
#75000
0#
06
#80000
1#
1$
b111101100110110111001011 %
b110010101010001001100010 &
b000011000110100111101101 '
b001010111000111011000010 )
b000101110111111011100101 *
b010001111011101110111101 +
b000000000000100011010001 -
b000000000000100111110111 .
b000000000000101000100101 /
b111001100000000000010111 0
05
16
17
b111101100110110111001011 8
b110010101010001001100010 9
b000011000110100111101101 :
b001010111000111011000010 <
b000101110111111011100101 =
b010001111011101110111101 >
b000000000000100011010001 @
b000000000000100111110111 A
b000000000000101000100101 B
b111001100000000000010111 C
0H
#85000
0#
06
#90000
1#
0$
b000100001010010010011110 1
b111100001000111011101111 2
b001010011010111010111010 3
15
16
07
b000100001010010010011110 D
b111100001000111011101111 E
b001010011010111010111010 F
1H
b1111111111111111111111111111110001110101110001100001101010001010 I
b0000000000000000000000000000011100101100000101011111001000011100 K
b0000000000000000000000000000001110001010001110011110010101110110 M
b0000000000000000000000000000011100101100000101011111001000011100 O
b0000000000000000000000000000000000000000000000000000011111100101 Q
b0000000000000000000000000000000000000000000000000000011111100101 S
#95000
0#
06
#100000
1#
1$
b001011110011010111111010 %
b001111111000101101110110 &
b110011111110000010100110 '
b110100111011011000000011 )
b010001111111110101111010 *
b001010101000101000100101 +
b000000000000100100001010 -
b000000000000001001010101 .
b000000000000101100000111 /
b111111001100011010101011 0
05
16
17
b001011110011010111111010 8
b001111111000101101110110 9
b110011111110000010100110 :
b110100111011011000000011 <
b010001111111110101111010 =
b001010101000101000100101 >
b000000000000100100001010 @
b000000000000001001010101 A
b000000000000101100000111 B
b111111001100011010101011 C
0H
#105000
0#
06
#110000
1#
0$
b001010111011111110010010 1
b001111111101110101000110 2
b110100110100111011101111 3
15
16
07
b001010111011111110010010 D
b001111111101110101000110 E
b110100110100111011101111 F
1H
b1111111111111111111111111111111111111000101011110001011001111100 I
b0000000000000000000000000000000011000000011000100100110000100111 K
b0000000000000000000000000000000000000111010100001110100110000100 M
b0000000000000000000000000000000011000000011000100100110000100111 O
b0000000000000000000000000000000000000000000000000000000010011011 Q
b0000000000000000000000000000000000000000000000000000000010011011 S
#115000
0#
06
#120000
1#
1$
b111110111001010110000010 %
b110111010111011011010111 &
b101100110101100101111111 '
b000100100000101101111000 )
b101111010100111100110110 *
b110110000001000001111000 +
b111111111111000001111010 -
b111111111111101101110100 .
b000000000000000011100101 /
b111101110111001001011001 0
05
16
17
b111110111001010110000010 8
b110111010111011011010111 9
b101100110101100101111111 :
b000100100000101101111000 <
b101111010100111100110110 =
b110110000001000001111000 >
b111111111111000001111010 @
b111111111111101101110100 A
b000000000000000011100101 B
b111101110111001001011001 C
0H
#125000
0#
06
#130000
1#
0$
b111111100011111111000001 1
b110110011010011000100011 2
b101101111011010010110100 3
15
16
07
b111111100011111111000001 D
b110110011010011000100011 E
b101101111011010010110100 F
1H
b0000000000000000000000000000000000010100001010010110010011111011 I
b1111111111111111111111111111111101010110011000001011010000000101 K
b1111111111111111111111111111111111101011110101101001101100000101 M
b1111111111111111111111111111111101010110011000001011010000000101 O
b0000000000000000000000000000000000000000000000000000000111100110 Q
b0000000000000000000000000000000000000000000000000000000111100110 S
#135000
0#
06
#140000
1#
1$
b001111100100001010010001 %
b110111111111110100000011 &
b111001100100100101101010 '
b111100110001100010010111 )
b001100010001101100001000 *
b000001111111110011110000 +
b000000000000001011000101 -
b000000000000101111001110 .
b111111111111001011000110 /
b111001100011101101010001 0
05
16
17
b001111100100001010010001 8
b110111111111110100000011 9
b111001100100100101101010 :
b111100110001100010010111 <
b001100010001101100001000 =
b000001111111110011110000 >
b000000000000001011000101 @
b000000000000101111001110 A
b111111111111001011000110 B
b111001100011101101010001 C
0H
#145000
0#
06
#150000
1#
0$
b111110011000100101111111 1
b001010100010011110000101 2
b000001010001100110011101 3
15
16
07
b111110011000100101111111 D
b001010100010011110000101 E
b000001010001100110011101 F
1H
b1111111111111111111111111111111011101010010110010010000011111011 I
b0000000000000000000000000000000100101111101001001010001101001000 K
b0000000000000000000000000000000100010101101001101101111100000101 M
b0000000000000000000000000000000100101111101001001010001101001000 O
b0000000000000000000000000000000000000000000000000000111010100001 Q
b0000000000000000000000000000000000000000000000000000111010100001 S
#155000
0#
06
#160000
1#
1$
b001111000101100101000000 %
b001111010010100000000010 &
b110100001101010111011111 '
b001011001011010111110110 )
b001111001010010011001101 *
b001110000111000011111010 +
b000000000000010011000011 -
b111111111111111101110110 .
b000000000000100110001110 /
b111011000010111000000010 0
05
16
17
b001111000101100101000000 8
b001111010010100000000010 9
b110100001101010111011111 :
b001011001011010111110110 <
b001111001010010011001101 =
b001110000111000011111010 >
b000000000000010011000011 @
b111111111111111101110110 A
b000000000000100110001110 B
b111011000010111000000010 C
0H
#165000
0#
06
#170000
1#
0$
b001100111001010100111000 1
b001111001101111001110101 2
b000010101110100101010000 3
15
16
07
b001100111001010100111000 D
b001111001101111001110101 E
b000010101110100101010000 F
1H
b1111111111111111111111111111110111111110101000010000001101011110 I
b0000000000000000000000000000001110010011101111000010110100101110 K
b0000000000000000000000000000001000000001010111101111110010100010 M
b0000000000000000000000000000001110010011101111000010110100101110 O
b0000000000000000000000000000000000000000000000000000100011111000 Q
b0000000000000000000000000000000000000000000000000000100011111000 S
#175000
0#
06
#180000
1#
1$
b001100110101011101010000 %
b111110010011111010110111 &
b001110011000000001100101 '
b110111100000111000011110 )
b010010110100001001010001 *
b110101001001011010000110 +
b111111111111101111110101 -
b111111111111111011010100 .
b111111111111111111100110 /
b111111100101000101100110 0
05
16
17
b001100110101011101010000 8
b111110010011111010110111 9
b001110011000000001100101 :
b110111100000111000011110 <
b010010110100001001010001 =
b110101001001011010000110 >
b111111111111101111110101 @
b111111111111111011010100 A
b111111111111111111100110 B
b111111100101000101100110 C
0H
#185000
0#
06
#190000
1#
0$
b111001101100110011011111 1
b010000101101100101110010 2
b110111101110111110000001 3
15
16
07
b111001101100110011011111 D
b010000101101100101110010 E
b110111101110111110000001 F
1H
b1111111111111111111111111111111100010111100101111101011011011010 I
b0000000000000000000000000000000100000010111100100111010101010100 K
b0000000000000000000000000000000011101000011010000010100100100110 M
b0000000000000000000000000000000100000010111100100111010101010100 O
b0000000000000000000000000000000000000000000000000000111001011100 Q
b0000000000000000000000000000000000000000000000000000111001011100 S
#195000
0#
06
#200000
1#
1$
b010001011111000000101111 %
b101111101010111111110100 &
b001110010001111111111100 '
b010000001111001111100100 )
b111001101101001001100110 *
b001101111111110010101100 +
b111111111111101001101000 -
b000000000000000011100101 .
b000000000000000100010011 /
b000101011100011010101110 0
05
16
17
b010001011111000000101111 8
b101111101010111111110100 9
b001110010001111111111100 :
b010000001111001111100100 <
b111001101101001001100110 =
b001101111111110010101100 >
b111111111111101001101000 @
b000000000000000011100101 A
b000000000000000100010011 B
b000101011100011010101110 C
0H
#205000
0#
06
#210000
1#
0$
b010000101100001100111011 1
b110110000100000001100100 2
b001110000110011001101101 3
15
16
07
b010000101100001100111011 D
b110110000100000001100100 E
b001110000110011001101101 F
1H
b1111111111111111111111111111111111011000001001000001101000010000 I
b0000000000000000000000000000000000111110100100010010010010010010 K
b0000000000000000000000000000000000100111110110111110010111110000 M
b0000000000000000000000000000000000111110100100010010010010010010 O
b0000000000000000000000000000000000000000000000000000101000110001 Q
b0000000000000000000000000000000000000000000000000000101000110001 S
#215000
0#
06
#220000
1#
1$
b010000111011110111110000 %
b000100001111010111010000 &
b111011001011010011101100 '
b111011001100000010011111 )
b111001010000011000000001 *
b010010001001001110001000 +
b000000000000101101001101 -
b000000000000111100011111 .
b111111111111000101101100 /
b000100001111000111001000 0
05
16
17
b010000111011110111110000 8
b000100001111010111010000 9
b111011001011010011101100 :
b111011001100000010011111 <
b111001010000011000000001 =
b010010001001001110001000 >
b000000000000101101001101 @
b000000000000111100011111 A
b111111111111000101101100 B
b000100001111000111001000 C
0H
#225000
0#
06
#230000
1#
0$
b000101011110001111001010 1
b111110011100110100011000 2
b000111010010000110010010 3
15
16
07
b000101011110001111001010 D
b111110011100110100011000 E
b000111010010000110010010 F
1H
b0000000000000000000000000000011000100110010111010110010011110000 I
b1111111111111111111111111111010001010101010010101110111001100010 K
b1111111111111111111111111111100111011001101000101001101100010000 M
b1111111111111111111111111111010001010101010010101110111001100010 O
b0000000000000000000000000000000000000000000000000000100001101111 Q
b0000000000000000000000000000000000000000000000000000100001101111 S
#235000
0#
06
#240000
1#
1$
b111001000110111001100100 %
b110001100011111010000101 &
b010011010111000010000001 '
b111001000010010000110001 )
b001001101010110100001101 *
b010001011011101000011000 +
b000000000000010110010011 -
b000000000000011100111000 .
b000000000000000000010100 /
b000101100111001000101000 0
05
16
17
b111001000110111001100100 8
b110001100011111010000101 9
b010011010111000010000001 :
b111001000010010000110001 <
b001001101010110100001101 =
b010001011011101000011000 >
b000000000000010110010011 @
b000000000000011100111000 A
b000000000000000000010100 B
b000101100111001000101000 C
0H
#245000
0#
06
#250000
1#
0$
b111001000101100001101111 1
b111000101100011100111001 2
b010010110010100001000111 3
15
16
07
b111001000101100001101111 D
b111000101100011100111001 E
b010010110010100001000111 F
1H
b1111111111111111111111111111111100110010100101011111000110011000 I
b0000000000000000000000000000001010110101111001100000101101000011 K
b0000000000000000000000000000000011001101011010100000111001101000 M
b0000000000000000000000000000001010110101111001100000101101000011 O
b0000000000000000000000000000000000000000000000000000010010111100 Q
b0000000000000000000000000000000000000000000000000000010010111100 S
#255000
0#
06
#260000
1#
1$
b010000110001111110011100 %
b101100010000110010011100 &
b000001110011010111011110 '
b101111001001000101011010 )
b111110111110000101110111 *
b101110110011001010011101 +
b000000000000011011010010 -
b111111111111101010111010 .
b000000000000001010010001 /
b111010110110111111111011 0
05
16
17
b010000110001111110011100 8
b101100010000110010011100 9
b000001110011010111011110 :
b101111001001000101011010 <
b111110111110000101110111 =
b101110110011001010011101 >
b000000000000011011010010 @
b111111111111101010111010 A
b000000000000001010010001 B
b111010110110111111111011 C
0H
#265000
0#
06
#270000
1#
0$
b000100001101010001001111 1
b110011010000010100001011 2
b111010101100110001100110 3
15
16
07
b000100001101010001001111 D
b110011010000010100001011 E
b111010101100110001100110 F
1H
b0000000000000000000000000000001000110011101001100000011000001110 I
b1111111111111111111111111111101000011100100101101110110100101001 K
b1111111111111111111111111111110111001100010110011111100111110010 M
b1111111111111111111111111111101000011100100101101110110100101001 O
b0000000000000000000000000000000000000000000000000000010111111011 Q
b0000000000000000000000000000000000000000000000000000010111111011 S
#275000
0#
06
#280000
1#
1$
b111111110011011100010111 %
b110110001010100110111101 &
b000101011111101100111011 '
b010001001100001101000100 )
b111111110111001100101100 *
b111000111110111010001011 +
b000000000000110011111111 -
b000000000000100101111111 .
b111111111111001011010110 /
b111100100000110001001111 0
05
16
17
b111111110011011100010111 8
b110110001010100110111101 9
b000101011111101100111011 :
b010001001100001101000100 <
b111111110111001100101100 =
b111000111110111010001011 >
b000000000000110011111111 @
b000000000000100101111111 A
b111111111111001011010110 B
b111100100000110001001111 C
0H
#285000
0#
06
#290000
1#
0$
b000111110111111000110101 1
b111010101010101000011001 2
b111111101100000010110111 3
15
16
07
b000111110111111000110101 D
b111010101010101000011001 E
b111111101100000010110111 F
1H
b1111111111111111111111111111110001111111101010001000011011111110 I
b0000000000000000000000000000011110001011000001101001011011000100 K
b0000000000000000000000000000001110000000010101110111100100000010 M
b0000000000000000000000000000011110001011000001101001011011000100 O
b0000000000000000000000000000000000000000000000000000011101101101 Q
b0000000000000000000000000000000000000000000000000000011101101101 S
#295000
0#
06
#300000
1#
1$
b000101110100100011101010 %
b111101111001010111000000 &
b110110110001111101100110 '
b000000010010001101111010 )
b110100001110110011001010 *
b101101001111100010100011 +
b000000000000101101101100 -
b000000000000000101000010 .
b111111111111110111101110 /
b111011110101010010100110 0
05
16
17
b000101110100100011101010 8
b111101111001010111000000 9
b110110110001111101100110 :
b000000010010001101111010 <
b110100001110110011001010 =
b101101001111100010100011 >
b000000000000101101101100 @
b000000000000000101000010 A
b111111111111110111101110 B
b111011110101010010100110 C
0H
#305000
0#
06
#310000
1#
0$
b000100001101000101111011 1
b111011000100101111101010 2
b110011111111101110010100 3
15
16
07
b000100001101000101111011 D
b111011000100101111101010 E
b110011111111101110010100 F
1H
b0000000000000000000000000000000001000001000000101000101100001100 I
b1111111111111111111111111111111100100001011010000001111100001010 K
b1111111111111111111111111111111110111110111111010111010011110100 M
b1111111111111111111111111111111100100001011010000001111100001010 O
b0000000000000000000000000000000000000000000000000000010010101100 Q
b0000000000000000000000000000000000000000000000000000010010101100 S
#315000
0#
06
#320000
1#
1$
b000010001000000001000011 %
b110111110110101011101110 &
b000010000000100010001110 '
b001000101001000111010000 )
b111001010000100000111011 *
b001101100010111000011000 +
b000000000000011111110101 -
b000000000000000000100101 .
b000000000000101000101110 /
b110110001101100000110010 0
05
16
17
b000010001000000001000011 8
b110111110110101011101110 9
b000010000000100010001110 :
b001000101001000111010000 <
b111001010000100000111011 =
b001101100010111000011000 >
b000000000000011111110101 @
b000000000000000000100101 A
b000000000000101000101110 B
b110110001101100000110010 C
0H
#325000
0#
06
#330000
1#
0$
b000110110000010101111011 1
b111000110110100000001111 2
b001010001101000101111001 3
15
16
07
b000110110000010101111011 D
b111000110110100000001111 E
b001010001101000101111001 F
1H
b1111111111111111111111111111111000011110001110010011111100001001 I
b0000000000000000000000000000001010100101111111111000010111011110 K
b0000000000000000000000000000000111100001110001101100000011110111 M
b0000000000000000000000000000001010100101111111111000010111011110 O
b0000000000000000000000000000000000000000000000000000101101011110 Q
b0000000000000000000000000000000000000000000000000000101101011110 S
#335000
0#
06
#340000
1#
1$
b001111011100011101001011 %
b111001110100011100110001 &
b000110010000110101111101 '
b110010001000010111001101 )
b010010101010011001001111 *
b001101101111011100001110 +
b000000000000110011011000 -
b000000000000110010010000 .
b111111111111001111000101 /
b000000101100101111100101 0
05
16
17
b001111011100011101001011 8
b111001110100011100110001 9
b000110010000110101111101 :
b110010001000010111001101 <
b010010101010011001001111 =
b001101101111011100001110 >
b000000000000110011011000 @
b000000000000110010010000 A
b111111111111001111000101 B
b000000101100101111100101 C
0H
#345000
0#
06
#350000
1#
0$
b000101000010111011111111 1
b000010101000011101011110 2
b001000111010100111100111 3
15
16
07
b000101000010111011111111 D
b000010101000011101011110 E
b001000111010100111100111 F
1H
b0000000000000000000000000000000011011101001111000101101100001001 I
b1111111111111111111111111111110110010000100000100001111000100101 K
b1111111111111111111111111111111100100010110000111010010011110111 M
b1111111111111111111111111111110110010000100000100001111000100101 O
b0000000000000000000000000000000000000000000000000000010110101101 Q
b0000000000000000000000000000000000000000000000000000010110101101 S
#355000
0#
06
#360000
1#
1$
b101100011011001101000101 %
b001101011011100110011000 &
b000001011011111001010100 '
b111010000001000001010110 )
b111010101000101001111101 *
b111001011011110110000111 +
b111111111111101000111110 -
b000000000000011000111100 .
b000000000000110100010110 /
b110111001000100000001100 0
05
16
17
b101100011011001101000101 8
b001101011011100110011000 9
b000001011011111001010100 :
b111010000001000001010110 <
b111010101000101001111101 =
b111001011011110110000111 >
b111111111111101000111110 @
b000000000000011000111100 A
b000000000000110100010110 B
b110111001000100000001100 C
0H
#365000
0#
06
#370000
1#
0$
b101111101111110001100011 1
b001000110101100111100100 2
b111111011110110000100001 3
15
16
07
b101111101111110001100011 D
b001000110101100111100100 E
b111111011110110000100001 F
1H
b0000000000000000000000000000000100100101011100000011101110001110 I
b1111111111111111111111111111101101001111011101111111110100101100 K
b1111111111111111111111111111111011011010100011111100010001110010 M
b1111111111111111111111111111101101001111011101111111110100101100 O
b0000000000000000000000000000000000000000000000000000001111101001 Q
b0000000000000000000000000000000000000000000000000000001111101001 S
#375000
0#
06
#380000
1#
1$
b111111100011011000010011 %
b000000000010111101111010 &
b000110011001010000010010 '
b101111010010011010011011 )
b110110111000001001101010 *
b101111101010111110010110 +
b000000000000001000110010 -
b111111111111001111010000 .
b111111111111100001000101 /
b110110101010111100011010 0
05
16
17
b111111100011011000010011 8
b000000000010111101111010 9
b000110011001010000010010 :
b101111010010011010011011 <
b110110111000001001101010 =
b101111101010111110010110 >
b000000000000001000110010 @
b111111111111001111010000 A
b111111111111100001000101 B
b110110101010111100011010 C
0H
#385000
0#
06
#390000
1#
0$
b110010100111011000100101 1
b111000110000001101010010 2
b110100010100100000010100 3
15
16
07
b110010100111011000100101 D
b111000110000001101010010 E
b110100010100100000010100 F
1H
b1111111111111111111111111111110011011111000001100000111110110000 I
b0000000000000000000000000000001111101110110011011000100000100100 K
b0000000000000000000000000000001100100000111110011111000001010000 M
b0000000000000000000000000000001111101110110011011000100000100100 O
b0000000000000000000000000000000000000000000000000000110010111010 Q
b0000000000000000000000000000000000000000000000000000110010111010 S
#395000
0#
06
#400000
1#
1$
b111010001010001100110010 %
b001111111000110111000100 &
b101100101000010101011101 '
b101100001010100000100010 )
b111010110000111011110000 *
b000101110111111010110101 +
b111111111111011001010111 -
b000000000000111001101101 .
b000000000000010100110010 /
b110100101111110110101101 0
05
16
17
b111010001010001100110010 8
b001111111000110111000100 9
b101100101000010101011101 :
b101100001010100000100010 <
b111010110000111011110000 =
b000101110111111010110101 >
b111111111111011001010111 @
b000000000000111001101101 A
b000000000000010100110010 B
b110100101111110110101101 C
0H
#405000
0#
06
#410000
1#
0$
b111000010110101111010100 1
b001101001010100101101010 2
b101111111000100110000001 3
15
16
07
b111000010110101111010100 D
b001101001010100101101010 E
b101111111000100110000001 F
1H
b0000000000000000000000000000000000010011110100110100001110011100 I
b1111111111111111111111111111111101100110011101100010000001111100 K
b1111111111111111111111111111111111101100001011001011110001100100 M
b1111111111111111111111111111111101100110011101100010000001111100 O
b0000000000000000000000000000000000000000000000000000001000010000 Q
b0000000000000000000000000000000000000000000000000000001000010000 S
#415000
0#
06
#420000
1#
1$
b111000001001111111100101 %
b111100011011110101011110 &
b001001110110010101001011 '
b010011000100100111011110 )
b000001110100100100001101 *
b111111101001111000001010 +
b111111111111010001101100 -
b111111111111110010111111 .
b111111111111101001111101 /
b000100001100001100101111 0
05
16
17
b111000001001111111100101 8
b111100011011110101011110 9
b001001110110010101001011 :
b010011000100100111011110 <
b000001110100100100001101 =
b111111101001111000001010 >
b111111111111010001101100 @
b111111111111110010111111 A
b111111111111101001111101 B
b000100001100001100101111 C
0H
#425000
0#
06
#430000
1#
0$
b000011100000101110011010 1
b111110101101010001001011 2
b000101100011000100111011 3
15
16
07
b000011100000101110011010 D
b111110101101010001001011 E
b000101100011000100111011 F
1H
b0000000000000000000000000000000111001100101110110010110101011101 I
b1111111111111111111111111111101110111100000110101011111111100000 K
b1111111111111111111111111111111000110011010001001101001010100011 M
b1111111111111111111111111111101110111100000110101011111111100000 O
b0000000000000000000000000000000000000000000000000000011011000000 Q
b0000000000000000000000000000000000000000000000000000011011000000 S
#435000
0#
06
#440000
1#
1$
b010011011010001000110110 %
b000000100000010111000101 &
b101110111001011011001110 '
b111110111101001011000110 )
b001010001000000010110011 *
b001011100101110100100100 +
b000000000000001011100111 -
b000000000000011101010100 .
b000000000000010001111101 /
b000000010100001010110010 0
05
16
17
b010011011010001000110110 8
b000000100000010111000101 9
b101110111001011011001110 :
b111110111101001011000110 <
b001010001000000010110011 =
b001011100101110100100100 >
b000000000000001011100111 @
b000000000000011101010100 A
b000000000000010001111101 B
b000000010100001010110010 C
0H
#445000
0#
06
#450000
1#
0$
b010001101100110110000100 1
b000001010011110001001000 2
b110001010010110000011101 3
15
16
07
b010001101100110110000100 D
b000001010011110001001000 E
b110001010010110000011101 F
1H
b1111111111111111111111111111111111010001010000110000110011110100 I
b0000000000000000000000000000001000101111101011111111101000000110 K
b0000000000000000000000000000000000101110101111001111001100001100 M
b0000000000000000000000000000001000101111101011111111101000000110 O
b0000000000000000000000000000000000000000000000000000000101010110 Q
b0000000000000000000000000000000000000000000000000000000101010110 S
#455000
0#
06
#460000
1#
1$
b111111000110011011011110 %
b111011001011010001000011 &
b110101101011010100100110 '
b111111111100100110000111 )
b101101001001100110101001 *
b000100000110111010010010 +
b111111111111100010000010 -
b111111111111111000010000 .
b000000000000001000010001 /
b000000000000100110100001 0
05
16
17
b111111000110011011011110 8
b111011001011010001000011 9
b110101101011010100100110 :
b111111111100100110000111 <
b101101001001100110101001 =
b000100000110111010010010 >
b111111111111100010000010 @
b111111111111111000010000 A
b000000000000001000010001 B
b000000000000100110100001 C
0H
#465000
0#
06
